<PAMDataset>
  <PAMRasterBand band="1">
    <Histograms>
      <HistItem>
        <HistMin>1272</HistMin>
        <HistMax>1845</HistMax>
        <BucketCount>256</BucketCount>
        <IncludeOutOfRange>1</IncludeOutOfRange>
        <Approximate>0</Approximate>
        <HistCounts>5|4|4|2|8|2|3|5|6|1|5|2|15|6|6|7|20|8|15|27|27|23|24|28|49|35|38|29|64|34|49|54|60|55|61|60|86|55|54|60|85|58|77|67|126|84|82|99|144|86|105|110|147|114|77|100|130|75|75|55|83|55|58|59|90|38|40|39|62|28|32|40|40|20|23|28|40|23|34|25|40|27|20|17|9|2|0|1|2|2|1|1|1|4|2|0|2|0|0|0|2|2|2|0|2|3|0|0|0|1|2|1|1|0|2|1|2|0|1|1|0|1|1|0|0|3|0|1|2|0|1|0|1|1|1|0|0|2|0|2|0|2|1|0|1|0|0|0|1|2|1|0|0|1|0|2|0|2|0|0|0|1|1|1|0|0|2|0|0|1|1|0|2|0|1|1|0|0|0|1|0|0|1|1|1|0|1|2|1|0|0|0|1|0|0|1|1|0|0|0|1|1|1|1|1|0|0|2|0|0|0|1|0|1|0|1|0|2|1|0|0|0|1|0|1|0|1|0|1|1|0|1|1|1|0|0|1|0|1|0|2|0|1|1|0|1|1|0|0|4|1|0|2|4|1|1</HistCounts>
      </HistItem>
    </Histograms>
    <Metadata>
      <MDI key="STATISTICS_COUNT">4096.000000</MDI>
      <MDI key="STATISTICS_COVARIANCES">3853.548610157187,7422.414108764449,8721.408182139015,12932.57628777469,10606.1286002842,4070.975167172242,2268.618042439295,1569.150789835074,587.2096525869614,23.38688377594625,11251.62363805892,11534.47441930888,1466.418364382984</MDI>
      <MDI key="STATISTICS_EXCLUDEDVALUES"></MDI>
      <MDI key="STATISTICS_MAXIMUM">1845</MDI>
      <MDI key="STATISTICS_MEAN">1390.7255859375</MDI>
      <MDI key="STATISTICS_MEDIAN">1384.352941</MDI>
      <MDI key="STATISTICS_MINIMUM">1272</MDI>
      <MDI key="STATISTICS_SKIPFACTORX">1</MDI>
      <MDI key="STATISTICS_SKIPFACTORY">1</MDI>
      <MDI key="STATISTICS_STDDEV">62.076957159297</MDI>
    </Metadata>
  </PAMRasterBand>
  <PAMRasterBand band="2">
    <Histograms>
      <HistItem>
        <HistMin>843</HistMin>
        <HistMax>3644</HistMax>
        <BucketCount>256</BucketCount>
        <IncludeOutOfRange>1</IncludeOutOfRange>
        <Approximate>0</Approximate>
        <HistCounts>3|5|4|10|20|25|41|38|46|78|83|99|114|113|98|104|115|117|96|127|122|133|114|111|101|85|75|69|76|82|83|78|74|61|80|63|63|52|57|44|35|43|46|49|47|37|39|37|46|36|32|42|32|33|27|29|30|31|29|33|17|31|20|14|13|16|11|18|10|7|8|11|10|11|9|7|12|5|4|6|5|2|7|5|7|4|4|3|6|2|3|4|4|3|2|5|5|2|4|1|0|5|6|4|1|4|1|1|5|1|1|0|0|0|3|1|4|0|0|1|2|3|0|3|4|2|2|1|3|1|4|1|0|2|3|1|0|1|1|3|0|0|0|0|1|0|0|0|0|0|0|1|1|0|0|0|1|0|0|0|0|0|1|0|0|0|0|0|0|0|0|0|0|0|0|0|0|0|0|0|0|0|0|0|0|1|0|0|0|0|0|1|0|0|0|0|2|0|0|0|0|0|0|0|0|0|0|0|0|0|0|0|0|0|0|0|0|0|0|0|0|0|0|0|0|0|0|0|0|0|0|0|0|0|0|0|0|0|0|0|0|0|0|0|0|0|0|0|0|0|0|0|0|0|0|2</HistCounts>
      </HistItem>
    </Histograms>
    <Metadata>
      <MDI key="STATISTICS_COUNT">4096.000000</MDI>
      <MDI key="STATISTICS_COVARIANCES">7422.414108764449,64921.35514513685,70555.58415202431,98504.59016426258,44953.24497994402,18664.55550487925,11619.89629824377,14880.56568414201,1414.345721249152,37.90184581043903,42810.02132781469,44776.50242948212,8410.238134944424</MDI>
      <MDI key="STATISTICS_EXCLUDEDVALUES"></MDI>
      <MDI key="STATISTICS_MAXIMUM">3644</MDI>
      <MDI key="STATISTICS_MEAN">1203.8227539063</MDI>
      <MDI key="STATISTICS_MEDIAN">1128.592157</MDI>
      <MDI key="STATISTICS_MINIMUM">843</MDI>
      <MDI key="STATISTICS_SKIPFACTORX">1</MDI>
      <MDI key="STATISTICS_SKIPFACTORY">1</MDI>
      <MDI key="STATISTICS_STDDEV">254.79669374844</MDI>
    </Metadata>
  </PAMRasterBand>
  <PAMRasterBand band="3">
    <Histograms>
      <HistItem>
        <HistMin>766</HistMin>
        <HistMax>3661</HistMax>
        <BucketCount>256</BucketCount>
        <IncludeOutOfRange>1</IncludeOutOfRange>
        <Approximate>0</Approximate>
        <HistCounts>3|1|5|6|7|8|14|34|39|34|44|59|71|67|83|82|65|105|84|84|99|87|95|89|95|121|111|86|97|99|103|94|91|67|106|63|69|52|46|72|55|57|56|45|56|60|43|37|47|27|34|47|39|40|35|39|36|38|18|31|23|33|29|21|23|26|24|17|26|18|24|16|18|19|12|19|14|11|10|11|12|9|5|5|6|6|5|5|9|6|4|7|8|2|7|1|3|5|2|1|2|0|1|1|8|3|1|2|2|5|3|3|2|2|0|4|3|1|1|2|2|1|4|0|2|1|1|0|3|2|4|2|3|3|1|1|1|1|0|0|2|1|2|2|0|2|1|1|2|1|0|0|0|1|2|1|2|0|2|0|0|1|0|0|2|1|2|1|1|1|1|2|0|0|0|0|1|0|0|0|0|0|0|0|0|0|0|0|0|0|0|0|0|0|0|0|0|0|0|0|0|0|0|0|0|0|0|0|0|0|0|2|0|0|0|0|0|0|0|0|0|0|0|0|0|0|0|0|0|0|0|0|0|0|0|0|0|0|0|0|0|0|0|0|0|0|0|0|0|0|0|0|0|0|0|2</HistCounts>
      </HistItem>
    </Histograms>
    <Metadata>
      <MDI key="STATISTICS_COUNT">4096.000000</MDI>
      <MDI key="STATISTICS_COVARIANCES">8721.408182139015,70555.58415202431,83089.5556106437,115008.4858583256,55555.41817443632,28420.33444284683,21963.6989379437,35557.88782623616,3440.527912755677,51.96486664377366,58396.4752972616,56996.67115682713,19746.92555743978</MDI>
      <MDI key="STATISTICS_EXCLUDEDVALUES"></MDI>
      <MDI key="STATISTICS_MAXIMUM">3661</MDI>
      <MDI key="STATISTICS_MEAN">1199.8100585937</MDI>
      <MDI key="STATISTICS_MEDIAN">1117.941176</MDI>
      <MDI key="STATISTICS_MINIMUM">766</MDI>
      <MDI key="STATISTICS_SKIPFACTORX">1</MDI>
      <MDI key="STATISTICS_SKIPFACTORY">1</MDI>
      <MDI key="STATISTICS_STDDEV">288.25258994612</MDI>
    </Metadata>
  </PAMRasterBand>
  <PAMRasterBand band="4">
    <Histograms>
      <HistItem>
        <HistMin>527</HistMin>
        <HistMax>4098</HistMax>
        <BucketCount>256</BucketCount>
        <IncludeOutOfRange>1</IncludeOutOfRange>
        <Approximate>0</Approximate>
        <HistCounts>3|6|6|18|13|11|27|34|29|38|42|76|57|71|73|73|67|72|68|78|86|66|55|81|80|85|84|77|78|52|80|74|55|67|76|85|58|70|59|70|72|56|54|49|59|42|45|45|33|30|44|43|42|39|31|31|25|39|29|46|33|39|30|27|29|25|32|29|36|29|24|23|26|16|19|26|14|13|24|19|21|18|18|15|12|21|14|10|11|12|10|12|13|10|8|11|10|5|5|6|7|8|3|4|10|5|3|5|3|3|3|6|5|3|1|2|5|1|4|1|3|4|4|5|3|3|2|4|1|3|3|4|0|1|0|3|2|0|2|2|0|1|0|0|3|1|3|1|2|1|2|0|1|1|0|1|0|1|0|0|2|2|3|1|0|0|1|2|1|1|1|1|0|0|0|0|0|1|0|0|0|1|1|1|0|0|1|0|1|0|1|0|1|1|0|0|0|1|1|1|0|0|3|0|0|1|1|0|2|1|0|1|0|0|0|0|0|0|0|0|0|0|0|0|0|0|0|0|0|0|0|0|0|0|0|0|0|0|0|0|0|0|0|0|0|0|0|0|0|0|0|0|0|0|0|2</HistCounts>
      </HistItem>
    </Histograms>
    <Metadata>
      <MDI key="STATISTICS_COUNT">4096.000000</MDI>
      <MDI key="STATISTICS_COVARIANCES">12932.57628777469,98504.59016426258,115008.4858583256,177275.3946543041,84079.66745507081,31810.17334067851,17732.9154175251,24652.09721459072,4255.020533806377,95.51203067765573,94247.58282060818,94843.23350551343,13907.87236864694</MDI>
      <MDI key="STATISTICS_EXCLUDEDVALUES"></MDI>
      <MDI key="STATISTICS_MAXIMUM">4098</MDI>
      <MDI key="STATISTICS_MEAN">1134.708984375</MDI>
      <MDI key="STATISTICS_MEDIAN">1031.141176</MDI>
      <MDI key="STATISTICS_MINIMUM">527</MDI>
      <MDI key="STATISTICS_SKIPFACTORX">1</MDI>
      <MDI key="STATISTICS_SKIPFACTORY">1</MDI>
      <MDI key="STATISTICS_STDDEV">421.04084677654</MDI>
    </Metadata>
  </PAMRasterBand>
  <PAMRasterBand band="5">
    <Histograms>
      <HistItem>
        <HistMin>1014</HistMin>
        <HistMax>3251</HistMax>
        <BucketCount>256</BucketCount>
        <IncludeOutOfRange>1</IncludeOutOfRange>
        <Approximate>0</Approximate>
        <HistCounts>2|2|0|2|2|1|2|6|2|6|13|13|15|12|31|23|40|31|38|47|46|53|74|58|49|72|72|64|68|74|66|68|84|78|69|49|84|64|79|65|88|84|65|55|64|81|75|93|56|75|71|62|61|68|60|50|69|46|45|74|61|45|48|50|43|35|38|31|26|39|27|36|24|30|27|30|28|23|22|20|24|17|14|14|20|20|17|16|11|12|7|13|12|9|18|6|8|6|9|10|4|12|6|8|3|6|4|7|7|3|10|6|2|1|0|3|3|3|4|2|3|3|1|1|0|1|1|0|1|3|2|1|1|2|3|2|2|2|0|0|1|0|4|2|0|0|1|0|0|0|1|0|1|3|1|0|1|0|2|1|0|0|2|1|0|1|1|2|0|3|0|3|1|0|1|0|1|0|0|1|0|0|2|1|0|1|0|1|0|0|1|0|0|0|0|0|2|0|0|0|0|0|0|1|0|0|1|0|1|0|0|1|0|1|0|0|1|0|0|0|1|2|0|0|0|1|0|0|1|0|0|0|0|1|0|0|0|1|0|0|1|0|0|0|0|2|0|0|1|0|0|0|0|0|0|1</HistCounts>
      </HistItem>
    </Histograms>
    <Metadata>
      <MDI key="STATISTICS_COUNT">4096.000000</MDI>
      <MDI key="STATISTICS_COVARIANCES">10606.1286002842,44953.24497994402,55555.41817443632,84079.66745507081,61020.47636211968,34649.86020078568,29743.9385482844,35014.44808550808,7666.162256038127,95.04556767017719,79380.83236839647,70040.45996040071,30751.30139228726</MDI>
      <MDI key="STATISTICS_EXCLUDEDVALUES"></MDI>
      <MDI key="STATISTICS_MAXIMUM">3251</MDI>
      <MDI key="STATISTICS_MEAN">1456.0236816406</MDI>
      <MDI key="STATISTICS_MEDIAN">1408.764706</MDI>
      <MDI key="STATISTICS_MINIMUM">1014</MDI>
      <MDI key="STATISTICS_SKIPFACTORX">1</MDI>
      <MDI key="STATISTICS_SKIPFACTORY">1</MDI>
      <MDI key="STATISTICS_STDDEV">247.02323040985</MDI>
    </Metadata>
  </PAMRasterBand>
  <PAMRasterBand band="6">
    <Histograms>
      <HistItem>
        <HistMin>1721</HistMin>
        <HistMax>3640</HistMax>
        <BucketCount>256</BucketCount>
        <IncludeOutOfRange>1</IncludeOutOfRange>
        <Approximate>0</Approximate>
        <HistCounts>1|1|0|0|0|1|1|3|0|2|1|1|0|1|0|1|1|1|0|1|3|1|3|0|1|0|5|1|2|0|1|1|3|4|5|3|3|9|10|6|3|6|13|10|19|8|6|18|8|21|16|21|23|27|26|34|18|28|28|33|31|28|40|26|40|35|38|38|55|47|44|36|52|45|52|55|47|48|70|57|47|53|58|53|51|69|52|64|59|78|48|60|54|60|43|56|59|60|56|48|54|45|41|44|58|58|52|45|54|33|56|37|31|35|41|35|33|34|25|42|18|26|29|16|18|27|21|18|17|17|20|20|13|17|12|17|9|15|18|17|21|19|11|12|20|10|12|7|4|8|10|10|8|10|11|12|10|10|6|11|11|6|2|4|4|6|3|1|3|6|2|4|5|3|6|4|4|3|1|4|2|4|4|6|3|2|1|3|3|1|3|3|1|5|2|3|2|2|4|2|3|0|0|8|0|3|2|2|0|4|1|1|4|1|3|2|2|0|2|0|3|0|1|1|0|0|3|0|2|2|0|0|1|2|3|2|0|2|0|0|0|0|1|0|0|0|0|0|0|1|0|0|0|0|0|1</HistCounts>
      </HistItem>
    </Histograms>
    <Metadata>
      <MDI key="STATISTICS_COUNT">4096.000000</MDI>
      <MDI key="STATISTICS_COVARIANCES">4070.975167172242,18664.55550487925,28420.33444284683,31810.17334067851,34649.86020078568,66474.08923080536,83528.01780438017,107755.8496766258,17580.02885497752,63.55746289301172,68519.4744049414,37096.71818761236,94404.43395891818</MDI>
      <MDI key="STATISTICS_EXCLUDEDVALUES"></MDI>
      <MDI key="STATISTICS_MAXIMUM">3640</MDI>
      <MDI key="STATISTICS_MEAN">2450.8605957031</MDI>
      <MDI key="STATISTICS_MEDIAN">2413.345098</MDI>
      <MDI key="STATISTICS_MINIMUM">1721</MDI>
      <MDI key="STATISTICS_SKIPFACTORX">1</MDI>
      <MDI key="STATISTICS_SKIPFACTORY">1</MDI>
      <MDI key="STATISTICS_STDDEV">257.82569544327</MDI>
    </Metadata>
  </PAMRasterBand>
  <PAMRasterBand band="7">
    <Histograms>
      <HistItem>
        <HistMin>1998</HistMin>
        <HistMax>4463</HistMax>
        <BucketCount>256</BucketCount>
        <IncludeOutOfRange>1</IncludeOutOfRange>
        <Approximate>0</Approximate>
        <HistCounts>1|1|1|2|0|2|0|3|1|1|0|1|0|2|1|4|1|5|1|0|0|4|1|2|3|1|1|4|5|1|2|7|4|10|8|6|10|14|8|10|18|8|10|9|13|28|15|19|29|38|30|34|22|25|33|44|29|33|38|30|44|43|42|44|52|37|43|44|43|49|40|54|58|51|67|59|66|46|68|61|66|52|75|44|61|65|58|64|77|67|65|60|44|55|63|52|52|49|38|53|48|45|37|60|35|35|44|31|32|37|35|40|27|17|23|23|13|26|25|23|25|17|19|18|20|12|11|19|12|13|13|12|10|7|13|12|12|6|13|12|9|14|12|11|13|9|9|13|8|7|14|12|9|6|7|2|9|10|7|4|5|8|6|3|5|4|6|6|6|5|2|4|3|2|2|1|0|2|0|2|5|6|1|3|2|1|2|2|2|3|2|3|1|0|1|7|2|3|0|1|3|4|1|1|1|1|0|2|1|2|0|1|0|4|2|1|2|1|1|1|0|0|0|1|0|1|1|0|0|2|0|0|1|3|0|1|2|0|0|0|1|1|1|1|0|1|0|0|0|1|3|2|2|0|1|1</HistCounts>
      </HistItem>
    </Histograms>
    <Metadata>
      <MDI key="STATISTICS_COUNT">4096.000000</MDI>
      <MDI key="STATISTICS_COVARIANCES">2268.618042439295,11619.89629824377,21963.6989379437,17732.9154175251,29743.9385482844,83528.01780438017,112177.4800842662,144214.6583571809,24190.69983616643,71.16982743818804,77292.21916536766,32691.7717153996,127991.3688077716</MDI>
      <MDI key="STATISTICS_EXCLUDEDVALUES"></MDI>
      <MDI key="STATISTICS_MAXIMUM">4463</MDI>
      <MDI key="STATISTICS_MEAN">2877.9963378906</MDI>
      <MDI key="STATISTICS_MEDIAN">2829.333333</MDI>
      <MDI key="STATISTICS_MINIMUM">1998</MDI>
      <MDI key="STATISTICS_SKIPFACTORX">1</MDI>
      <MDI key="STATISTICS_SKIPFACTORY">1</MDI>
      <MDI key="STATISTICS_STDDEV">334.929067243</MDI>
    </Metadata>
  </PAMRasterBand>
  <PAMRasterBand band="8">
    <Histograms>
      <HistItem>
        <HistMin>1152</HistMin>
        <HistMax>5066</HistMax>
        <BucketCount>256</BucketCount>
        <IncludeOutOfRange>1</IncludeOutOfRange>
        <Approximate>0</Approximate>
        <HistCounts>1|0|0|0|1|1|1|0|1|0|0|1|0|1|0|0|1|3|2|0|1|1|0|2|0|2|2|0|2|2|3|4|2|3|2|4|1|2|2|2|2|1|5|3|5|4|5|3|8|4|7|6|6|5|14|8|7|9|12|10|13|10|16|19|16|22|19|22|27|19|29|38|36|30|27|36|51|48|38|51|55|60|51|62|46|58|58|59|69|48|50|65|72|78|67|63|56|65|53|63|48|49|66|68|48|51|61|44|48|40|46|49|45|41|51|42|40|31|37|34|29|44|46|43|36|39|42|25|38|13|38|25|23|24|29|25|17|26|20|20|24|28|20|26|26|12|17|12|25|15|15|14|10|15|20|10|10|12|13|11|6|14|7|15|7|8|9|7|3|9|6|7|5|5|5|3|6|2|7|10|6|3|3|5|4|3|5|6|4|5|3|2|7|4|5|2|3|3|2|1|4|0|2|1|0|3|2|4|0|4|3|0|0|0|3|0|1|2|1|1|1|1|3|0|0|1|0|0|1|2|1|2|0|3|2|1|0|0|4|0|1|1|0|1|0|0|1|2|1|1|0|1|1|0|0|1</HistCounts>
      </HistItem>
    </Histograms>
    <Metadata>
      <MDI key="STATISTICS_COUNT">4096.000000</MDI>
      <MDI key="STATISTICS_COVARIANCES">1569.150789835074,14880.56568414201,35557.88782623616,24652.09721459072,35014.44808550808,107755.8496766258,144214.6583571809,266646.3010836375,26890.0303685895,81.63068528693526,91247.18904246774,36381.3226314482,165041.2370869586</MDI>
      <MDI key="STATISTICS_EXCLUDEDVALUES"></MDI>
      <MDI key="STATISTICS_MAXIMUM">5066</MDI>
      <MDI key="STATISTICS_MEAN">2797.46484375</MDI>
      <MDI key="STATISTICS_MEDIAN">2717.600000</MDI>
      <MDI key="STATISTICS_MINIMUM">1152</MDI>
      <MDI key="STATISTICS_SKIPFACTORX">1</MDI>
      <MDI key="STATISTICS_SKIPFACTORY">1</MDI>
      <MDI key="STATISTICS_STDDEV">516.37806022684</MDI>
    </Metadata>
  </PAMRasterBand>
  <PAMRasterBand band="9">
    <Histograms>
      <HistItem>
        <HistMin>886</HistMin>
        <HistMax>1443</HistMax>
        <BucketCount>256</BucketCount>
        <IncludeOutOfRange>1</IncludeOutOfRange>
        <Approximate>0</Approximate>
        <HistCounts>7|4|7|6|10|12|18|11|14|19|32|25|15|27|30|23|35|37|32|24|34|45|39|43|55|41|46|70|53|52|65|49|72|56|63|82|68|126|108|90|103|75|101|127|65|86|87|94|123|62|57|50|54|36|63|33|39|33|30|43|16|11|14|9|12|19|17|7|9|15|9|12|18|6|8|18|19|12|11|13|14|19|14|12|13|16|22|18|13|17|12|9|12|7|3|6|9|11|5|3|7|6|2|8|5|7|8|6|8|6|4|3|2|10|2|2|10|7|8|6|7|3|1|5|8|7|2|4|8|5|8|4|5|3|8|11|7|5|7|4|8|9|2|6|5|6|7|7|5|11|6|11|6|7|5|12|10|13|4|10|8|6|11|4|6|1|6|1|2|3|8|3|2|7|5|2|2|3|3|4|3|0|1|3|4|7|3|2|1|4|2|3|2|3|0|6|3|3|5|5|3|3|1|4|0|5|3|1|2|2|3|6|1|0|3|2|2|3|0|2|2|1|1|0|1|1|0|0|1|0|2|0|0|2|1|0|1|0|3|3|0|0|0|0|1|1|0|0|1|1|0|1|0|1|2|1</HistCounts>
      </HistItem>
    </Histograms>
    <Metadata>
      <MDI key="STATISTICS_COUNT">4096.000000</MDI>
      <MDI key="STATISTICS_COVARIANCES">587.2096525869614,1414.345721249152,3440.527912755677,4255.020533806377,7666.162256038127,17580.02885497752,24190.69983616643,26890.0303685895,9849.129486225491,39.42871833028095,28610.67327366642,13509.04959673562,30057.67593268286</MDI>
      <MDI key="STATISTICS_EXCLUDEDVALUES"></MDI>
      <MDI key="STATISTICS_MAXIMUM">1443</MDI>
      <MDI key="STATISTICS_MEAN">1014.6552734375</MDI>
      <MDI key="STATISTICS_MEDIAN">979.925490</MDI>
      <MDI key="STATISTICS_MINIMUM">886</MDI>
      <MDI key="STATISTICS_SKIPFACTORX">1</MDI>
      <MDI key="STATISTICS_SKIPFACTORY">1</MDI>
      <MDI key="STATISTICS_STDDEV">99.242780524457</MDI>
    </Metadata>
  </PAMRasterBand>
  <PAMRasterBand band="10">
    <Histograms>
      <HistItem>
        <HistMin>11</HistMin>
        <HistMax>17</HistMax>
        <BucketCount>256</BucketCount>
        <IncludeOutOfRange>1</IncludeOutOfRange>
        <Approximate>0</Approximate>
        <HistCounts>140|0|0|0|0|0|0|0|0|0|0|0|0|0|0|0|0|0|0|0|0|0|0|0|0|0|0|0|0|0|0|0|0|0|0|0|0|0|0|0|0|0|1343|0|0|0|0|0|0|0|0|0|0|0|0|0|0|0|0|0|0|0|0|0|0|0|0|0|0|0|0|0|0|0|0|0|0|0|0|0|0|0|0|0|0|1529|0|0|0|0|0|0|0|0|0|0|0|0|0|0|0|0|0|0|0|0|0|0|0|0|0|0|0|0|0|0|0|0|0|0|0|0|0|0|0|0|0|727|0|0|0|0|0|0|0|0|0|0|0|0|0|0|0|0|0|0|0|0|0|0|0|0|0|0|0|0|0|0|0|0|0|0|0|0|0|0|0|0|0|0|328|0|0|0|0|0|0|0|0|0|0|0|0|0|0|0|0|0|0|0|0|0|0|0|0|0|0|0|0|0|0|0|0|0|0|0|0|0|0|0|0|0|28|0|0|0|0|0|0|0|0|0|0|0|0|0|0|0|0|0|0|0|0|0|0|0|0|0|0|0|0|0|0|0|0|0|0|0|0|0|0|0|0|0|0|1</HistCounts>
      </HistItem>
    </Histograms>
    <Metadata>
      <MDI key="STATISTICS_COUNT">4096.000000</MDI>
      <MDI key="STATISTICS_COVARIANCES">23.38688377594625,37.90184581043903,51.96486664377366,95.51203067765573,95.04556767017719,63.55746289301172,71.16982743818804,81.63068528693526,39.42871833028095,1.026705586080591,247.2265086042455,167.8723896329369,99.03649505876265</MDI>
      <MDI key="STATISTICS_EXCLUDEDVALUES"></MDI>
      <MDI key="STATISTICS_MAXIMUM">17</MDI>
      <MDI key="STATISTICS_MEAN">12.962890625</MDI>
      <MDI key="STATISTICS_MEDIAN">13.000000</MDI>
      <MDI key="STATISTICS_MINIMUM">11</MDI>
      <MDI key="STATISTICS_SKIPFACTORX">1</MDI>
      <MDI key="STATISTICS_SKIPFACTORY">1</MDI>
      <MDI key="STATISTICS_STDDEV">1.0132648153768</MDI>
    </Metadata>
  </PAMRasterBand>
  <PAMRasterBand band="11">
    <Histograms>
      <HistItem>
        <HistMin>1447</HistMin>
        <HistMax>4511</HistMax>
        <BucketCount>256</BucketCount>
        <IncludeOutOfRange>1</IncludeOutOfRange>
        <Approximate>0</Approximate>
        <HistCounts>2|0|0|3|0|2|3|4|6|8|7|8|11|11|17|17|21|15|39|38|33|41|39|49|45|55|47|52|63|63|64|58|58|48|67|61|60|55|65|56|70|58|61|45|66|68|48|73|72|87|54|80|40|67|50|54|59|56|42|48|41|52|40|42|40|41|34|23|30|33|26|27|31|38|24|30|24|25|20|22|24|28|22|20|24|19|17|7|18|24|11|16|12|12|15|14|16|14|16|23|15|14|20|14|18|9|16|13|16|17|20|13|10|19|21|22|18|17|11|10|9|9|15|12|14|9|13|9|16|7|9|8|8|8|15|7|12|7|12|13|5|8|7|2|8|4|3|3|3|2|3|1|0|1|0|1|0|2|0|1|0|1|0|0|0|0|0|1|0|1|1|1|0|1|1|0|0|2|0|0|0|0|1|0|0|0|1|0|0|1|0|0|1|1|0|0|0|0|1|1|1|0|1|1|0|0|1|0|0|0|0|0|1|0|1|0|0|0|1|0|0|1|0|0|1|0|0|1|0|0|0|0|0|1|1|1|0|0|0|0|1|0|0|0|0|0|0|1|0|0|0|1|0|0|0|1</HistCounts>
      </HistItem>
    </Histograms>
    <Metadata>
      <MDI key="STATISTICS_COUNT">4096.000000</MDI>
      <MDI key="STATISTICS_COVARIANCES">11251.62363805892,42810.02132781469,58396.4752972616,94247.58282060818,79380.83236839647,68519.4744049414,77292.21916536766,91247.18904246774,28610.67327366642,247.2265086042455,171730.2500314201,121295.4492256064,94806.65979764151</MDI>
      <MDI key="STATISTICS_EXCLUDEDVALUES"></MDI>
      <MDI key="STATISTICS_MAXIMUM">4511</MDI>
      <MDI key="STATISTICS_MEAN">2174.3654785156</MDI>
      <MDI key="STATISTICS_MEDIAN">2059.800000</MDI>
      <MDI key="STATISTICS_MINIMUM">1447</MDI>
      <MDI key="STATISTICS_SKIPFACTORX">1</MDI>
      <MDI key="STATISTICS_SKIPFACTORY">1</MDI>
      <MDI key="STATISTICS_STDDEV">414.40348699235</MDI>
    </Metadata>
  </PAMRasterBand>
  <PAMRasterBand band="12">
    <Histograms>
      <HistItem>
        <HistMin>747</HistMin>
        <HistMax>3428</HistMax>
        <BucketCount>256</BucketCount>
        <IncludeOutOfRange>1</IncludeOutOfRange>
        <Approximate>0</Approximate>
        <HistCounts>4|0|1|1|2|0|1|4|2|6|4|7|16|14|10|18|20|32|28|25|33|33|31|39|33|32|38|47|38|55|48|54|54|58|50|46|60|54|51|51|54|43|70|53|66|62|53|55|76|59|58|35|44|56|55|44|57|61|66|57|50|52|73|45|68|46|55|50|53|43|53|51|47|50|39|38|36|31|33|38|32|30|29|27|30|28|20|40|25|26|22|33|30|40|23|33|20|24|32|18|17|17|16|21|15|11|10|17|9|20|9|7|13|8|3|8|3|8|8|5|6|6|9|6|4|7|6|2|4|7|3|3|1|0|1|0|5|1|0|2|1|2|1|1|0|2|1|0|1|1|2|1|1|3|0|3|0|1|1|3|2|0|1|0|1|0|0|0|1|0|1|0|0|1|0|1|0|1|1|1|0|0|0|1|0|0|0|1|0|2|0|0|0|0|0|0|1|0|1|0|1|0|0|1|0|0|1|1|1|0|0|0|0|0|1|0|0|0|0|0|0|1|2|0|0|0|0|0|1|1|0|0|1|1|0|0|0|1|0|0|1|0|0|0|1|0|0|0|0|1|1|0|0|0|0|1</HistCounts>
      </HistItem>
    </Histograms>
    <Metadata>
      <MDI key="STATISTICS_COUNT">4096.000000</MDI>
      <MDI key="STATISTICS_COVARIANCES">11534.47441930888,44776.50242948212,56996.67115682713,94843.23350551343,70040.45996040071,37096.71818761236,32691.7717153996,36381.3226314482,13509.04959673562,167.8723896329369,121295.4492256064,102196.437010109,38575.36341175676</MDI>
      <MDI key="STATISTICS_EXCLUDEDVALUES"></MDI>
      <MDI key="STATISTICS_MAXIMUM">3428</MDI>
      <MDI key="STATISTICS_MEAN">1383.3449707031</MDI>
      <MDI key="STATISTICS_MEDIAN">1346.282353</MDI>
      <MDI key="STATISTICS_MINIMUM">747</MDI>
      <MDI key="STATISTICS_SKIPFACTORX">1</MDI>
      <MDI key="STATISTICS_SKIPFACTORY">1</MDI>
      <MDI key="STATISTICS_STDDEV">319.68177459797</MDI>
    </Metadata>
  </PAMRasterBand>
  <PAMRasterBand band="13">
    <Histograms>
      <HistItem>
        <HistMin>2131</HistMin>
        <HistMax>5027</HistMax>
        <BucketCount>256</BucketCount>
        <IncludeOutOfRange>1</IncludeOutOfRange>
        <Approximate>0</Approximate>
        <HistCounts>1|0|1|0|3|3|0|2|0|0|0|0|0|1|0|4|1|2|0|1|2|0|2|3|4|2|4|4|3|2|8|3|2|5|8|4|12|9|10|18|15|20|22|19|21|25|23|33|37|35|26|27|38|42|35|42|51|48|49|36|38|45|65|39|58|49|34|63|39|54|57|74|54|74|63|75|60|79|69|79|75|82|69|52|69|59|65|60|60|44|46|45|45|43|53|62|22|43|50|33|42|36|37|56|27|31|31|22|25|33|24|17|23|25|16|29|10|22|8|19|22|5|16|13|10|12|16|11|23|5|12|8|13|17|7|6|10|10|9|6|11|5|11|5|16|9|4|5|11|10|11|10|8|6|10|7|5|4|7|3|9|5|11|5|2|3|0|3|4|8|4|4|4|4|3|1|3|1|1|0|2|5|2|0|0|0|0|2|2|0|4|2|1|0|1|2|3|0|4|0|3|0|1|1|5|3|0|1|1|0|3|1|1|2|0|2|2|0|2|0|1|1|1|0|1|2|1|0|0|0|1|0|0|0|1|2|1|0|3|0|0|0|2|1|0|0|0|1|1|0|1|1|2|2|1|1</HistCounts>
      </HistItem>
    </Histograms>
    <Metadata>
      <MDI key="STATISTICS_COUNT">4096.000000</MDI>
      <MDI key="STATISTICS_COVARIANCES">1466.418364382984,8410.238134944424,19746.92555743978,13907.87236864694,30751.30139228726,94404.43395891818,127991.3688077716,165041.2370869586,30057.67593268286,99.03649505876265,94806.65979764151,38575.36341175676,150319.8257334961</MDI>
      <MDI key="STATISTICS_EXCLUDEDVALUES"></MDI>
      <MDI key="STATISTICS_MAXIMUM">5027</MDI>
      <MDI key="STATISTICS_MEAN">3121.8845214844</MDI>
      <MDI key="STATISTICS_MEDIAN">3050.905882</MDI>
      <MDI key="STATISTICS_MINIMUM">2131</MDI>
      <MDI key="STATISTICS_SKIPFACTORX">1</MDI>
      <MDI key="STATISTICS_SKIPFACTORY">1</MDI>
      <MDI key="STATISTICS_STDDEV">387.71100801176</MDI>
    </Metadata>
  </PAMRasterBand>
</PAMDataset>
