<PAMDataset>
  <PAMRasterBand band="1">
    <Histograms>
      <HistItem>
        <HistMin>-0.5</HistMin>
        <HistMax>1181.5</HistMax>
        <BucketCount>1182</BucketCount>
        <IncludeOutOfRange>1</IncludeOutOfRange>
        <Approximate>0</Approximate>
        <HistCounts>0|0|0|0|0|0|0|0|0|0|0|0|0|0|0|0|0|0|0|0|0|0|0|0|0|0|0|0|0|0|0|0|0|0|0|0|0|0|0|0|0|0|0|0|0|0|0|0|0|0|0|0|0|0|0|0|0|0|0|0|0|0|0|0|0|0|0|0|0|0|0|0|0|0|0|0|0|0|0|0|0|0|0|0|0|0|0|0|0|0|0|0|0|0|0|0|0|0|0|0|0|0|0|0|0|0|0|0|0|0|0|0|0|0|0|0|0|0|0|0|0|0|0|0|0|0|0|0|0|0|0|0|0|0|0|0|0|0|0|0|0|0|0|0|0|0|0|0|0|0|0|0|0|0|0|0|0|0|0|0|0|0|0|0|0|0|0|0|0|0|0|0|0|0|0|0|0|0|0|0|0|0|0|0|0|0|0|0|0|0|0|0|0|0|0|0|0|0|0|0|0|0|0|0|0|0|0|0|0|0|0|0|0|0|0|0|0|0|0|0|0|0|0|0|0|0|0|0|0|0|0|0|0|0|0|0|0|0|0|0|0|0|0|0|0|0|0|0|0|0|0|0|0|0|0|0|0|0|0|0|0|0|0|0|0|0|0|0|0|0|0|0|0|0|0|0|0|0|0|0|0|0|0|0|0|0|0|0|0|0|0|0|0|0|0|0|0|0|0|0|0|0|0|0|0|0|0|0|0|0|0|0|0|0|0|0|0|0|0|0|0|0|0|0|0|0|0|0|0|0|0|0|0|0|0|0|0|0|0|0|0|0|0|0|0|0|0|0|0|0|0|0|0|0|0|0|0|0|0|0|0|0|0|0|0|0|0|0|0|0|0|0|0|0|0|0|0|0|0|0|0|0|0|0|0|0|0|0|0|0|0|0|0|0|0|0|0|0|0|0|0|0|0|0|0|0|0|0|0|0|0|0|0|0|0|0|0|0|0|0|0|0|0|0|0|0|0|0|0|0|0|0|0|0|0|0|0|0|0|0|0|0|0|0|0|0|0|0|0|0|0|0|0|0|0|0|0|0|0|0|0|0|0|0|0|0|0|0|0|0|0|0|0|0|0|0|0|0|0|0|0|0|0|0|0|0|0|0|0|0|0|0|0|0|0|0|0|0|0|0|0|0|0|0|0|0|0|0|0|0|0|0|0|0|0|0|0|0|0|0|0|0|0|0|0|0|0|0|0|0|0|0|0|0|0|0|0|0|0|0|0|0|0|0|0|0|0|0|0|0|0|0|0|0|0|0|0|0|0|0|0|0|0|0|0|0|0|0|0|0|0|0|0|0|0|0|0|0|0|0|0|0|0|0|0|0|0|0|0|0|0|0|0|0|0|0|0|0|0|0|0|0|0|0|0|0|0|0|0|0|0|0|0|0|0|0|0|0|0|0|0|0|0|0|0|0|0|0|0|0|0|0|0|0|0|0|0|0|0|0|0|0|0|0|0|0|0|0|0|0|0|0|0|0|0|0|0|0|0|0|0|0|0|0|0|0|0|0|0|0|0|0|0|0|0|0|0|0|0|0|0|0|0|0|0|0|0|0|0|0|0|0|0|0|0|0|0|0|0|0|0|0|0|0|0|0|0|0|0|0|0|0|0|0|0|0|0|0|0|0|0|0|0|0|0|0|0|0|0|0|0|0|0|0|0|0|0|0|0|0|0|0|0|0|0|0|0|0|0|0|0|0|0|0|0|0|0|0|0|0|0|0|0|0|0|0|0|0|0|0|0|0|0|0|0|0|0|0|0|0|0|0|0|0|0|0|0|0|0|0|0|0|0|0|0|0|0|0|0|0|0|0|0|0|0|0|0|0|0|0|0|0|0|0|0|0|0|0|0|0|0|0|0|0|0|0|0|0|0|0|0|0|0|0|0|0|0|0|0|0|0|0|0|0|0|0|0|0|0|0|0|0|0|0|0|0|0|0|0|0|0|0|0|0|0|0|0|0|0|0|0|0|0|0|0|0|0|0|0|0|0|0|0|0|0|0|0|0|0|0|0|0|0|0|0|0|0|0|0|0|0|0|0|0|0|0|0|0|0|0|0|0|0|0|0|0|0|0|0|0|0|0|0|0|0|0|0|0|0|0|0|0|0|0|0|0|0|0|0|0|0|0|0|0|0|0|0|0|0|0|0|0|0|0|0|0|0|0|0|0|0|0|0|0|0|0|0|0|0|0|0|0|0|0|0|0|0|0|0|0|0|0|0|0|0|0|0|0|0|0|0|0|0|0|0|0|0|0|0|0|0|0|0|0|0|0|0|0|0|0|0|0|0|0|0|0|0|0|0|0|0|0|0|0|0|0|0|0|0|0|0|0|0|0|0|0|0|0|0|0|0|0|0|0|0|0|0|0|0|0|0|0|0|0|0|0|0|0|0|0|0|0|0|0|0|0|0|0|0|0|0|0|0|0|0|0|0|0|0|0|0|0|0|0|0|0|0|0|0|0|0|0|0|0|0|0|0|0|0|0|0|0|0|0|0|0|0|0|0|0|0|0|0|0|0|0|0|0|0|0|0|22|54|59|62|106|92|104|90|104|111|100|99|100|114|139|164|201|197|249|158|139|77|81|70|53|54|48|41|39|44|34|37|36|75|104|119|106|74|56|51|50|59|44|27|28|20|24|18|21|15|20|17|11|12|9|10|15|4|11|12|6</HistCounts>
      </HistItem>
    </Histograms>
    <Metadata>
      <MDI key="STATISTICS_COUNT">4096.000000</MDI>
      <MDI key="STATISTICS_COVARIANCES">172.3474759019279,123.7053683512716,225.7128897307203,262.6004166785953,511.3031942178945,1216.119111232694,1549.965719317505,1605.777711481155,304.5766976567097,-2.678530947134806,1736.991524832612,774.2280408773222,1949.552840675946</MDI>
      <MDI key="STATISTICS_EXCLUDEDVALUES"></MDI>
      <MDI key="STATISTICS_MAXIMUM">1181</MDI>
      <MDI key="STATISTICS_MEAN">1142.2380371094</MDI>
      <MDI key="STATISTICS_MEDIAN">1139.000000</MDI>
      <MDI key="STATISTICS_MINIMUM">1121</MDI>
      <MDI key="STATISTICS_SKIPFACTORX">1</MDI>
      <MDI key="STATISTICS_SKIPFACTORY">1</MDI>
      <MDI key="STATISTICS_STDDEV">13.128117759295</MDI>
    </Metadata>
  </PAMRasterBand>
  <PAMRasterBand band="2">
    <Histograms>
      <HistItem>
        <HistMin>-0.5</HistMin>
        <HistMax>1006.5</HistMax>
        <BucketCount>1007</BucketCount>
        <IncludeOutOfRange>1</IncludeOutOfRange>
        <Approximate>0</Approximate>
        <HistCounts>0|0|0|0|0|0|0|0|0|0|0|0|0|0|0|0|0|0|0|0|0|0|0|0|0|0|0|0|0|0|0|0|0|0|0|0|0|0|0|0|0|0|0|0|0|0|0|0|0|0|0|0|0|0|0|0|0|0|0|0|0|0|0|0|0|0|0|0|0|0|0|0|0|0|0|0|0|0|0|0|0|0|0|0|0|0|0|0|0|0|0|0|0|0|0|0|0|0|0|0|0|0|0|0|0|0|0|0|0|0|0|0|0|0|0|0|0|0|0|0|0|0|0|0|0|0|0|0|0|0|0|0|0|0|0|0|0|0|0|0|0|0|0|0|0|0|0|0|0|0|0|0|0|0|0|0|0|0|0|0|0|0|0|0|0|0|0|0|0|0|0|0|0|0|0|0|0|0|0|0|0|0|0|0|0|0|0|0|0|0|0|0|0|0|0|0|0|0|0|0|0|0|0|0|0|0|0|0|0|0|0|0|0|0|0|0|0|0|0|0|0|0|0|0|0|0|0|0|0|0|0|0|0|0|0|0|0|0|0|0|0|0|0|0|0|0|0|0|0|0|0|0|0|0|0|0|0|0|0|0|0|0|0|0|0|0|0|0|0|0|0|0|0|0|0|0|0|0|0|0|0|0|0|0|0|0|0|0|0|0|0|0|0|0|0|0|0|0|0|0|0|0|0|0|0|0|0|0|0|0|0|0|0|0|0|0|0|0|0|0|0|0|0|0|0|0|0|0|0|0|0|0|0|0|0|0|0|0|0|0|0|0|0|0|0|0|0|0|0|0|0|0|0|0|0|0|0|0|0|0|0|0|0|0|0|0|0|0|0|0|0|0|0|0|0|0|0|0|0|0|0|0|0|0|0|0|0|0|0|0|0|0|0|0|0|0|0|0|0|0|0|0|0|0|0|0|0|0|0|0|0|0|0|0|0|0|0|0|0|0|0|0|0|0|0|0|0|0|0|0|0|0|0|0|0|0|0|0|0|0|0|0|0|0|0|0|0|0|0|0|0|0|0|0|0|0|0|0|0|0|0|0|0|0|0|0|0|0|0|0|0|0|0|0|0|0|0|0|0|0|0|0|0|0|0|0|0|0|0|0|0|0|0|0|0|0|0|0|0|0|0|0|0|0|0|0|0|0|0|0|0|0|0|0|0|0|0|0|0|0|0|0|0|0|0|0|0|0|0|0|0|0|0|0|0|0|0|0|0|0|0|0|0|0|0|0|0|0|0|0|0|0|0|0|0|0|0|0|0|0|0|0|0|0|0|0|0|0|0|0|0|0|0|0|0|0|0|0|0|0|0|0|0|0|0|0|0|0|0|0|0|0|0|0|0|0|0|0|0|0|0|0|0|0|0|0|0|0|0|0|0|0|0|0|0|0|0|0|0|0|0|0|0|0|0|0|0|0|0|0|0|0|0|0|0|0|0|0|0|0|0|0|0|0|0|0|0|0|0|0|0|0|0|0|0|0|0|0|0|0|0|0|0|0|0|0|0|0|0|0|0|0|0|0|0|0|0|0|0|0|0|0|0|0|0|0|0|0|0|0|0|0|0|0|0|0|0|0|0|0|0|0|0|0|0|0|0|0|0|0|0|0|0|0|0|0|0|0|0|0|0|0|0|0|0|0|0|0|0|0|0|0|0|0|0|0|0|0|0|0|0|0|0|0|0|0|0|0|0|0|0|0|0|0|0|0|0|0|0|0|0|0|0|0|0|0|0|0|0|0|0|0|0|0|0|0|0|0|0|1|1|0|1|0|0|2|3|2|3|1|1|6|3|10|14|16|8|13|18|29|24|31|39|48|41|45|35|69|52|59|63|53|84|81|88|79|60|91|100|110|95|93|85|80|70|103|93|95|85|75|89|105|109|69|68|92|78|82|82|70|83|56|53|64|60|56|44|30|48|39|30|30|30|27|28|20|13|21|16|19|17|14|17|12|17|5|6|6|14|10|5|3|6|5|5|1|6|2|8|3|3|1|2|5|0|4|0|3|3|1|1|0|0|0|0|0|0|0|1|0|0|0|0|1|3|0|0|0|2|0|1|0|0|2|0|0|1|0|1|0|0|0|1|0|0|1|0|0|0|0|2|1|0|0|0|0|0|1|3|0|0|0|0|0|0|0|1|0|1|0|0|0|0|1|0|0|1|0|1|1|0|0|0|0|0|0|0|0|0|1|0|0|1|0|0|0|0|1|2|0|1|2|1|0|1|0|1|0|0|0|0|0|0|1|1|0|0|0|1|0|0|0|0|0|0|0|1</HistCounts>
      </HistItem>
    </Histograms>
    <Metadata>
      <MDI key="STATISTICS_COUNT">4096.000000</MDI>
      <MDI key="STATISTICS_COVARIANCES">123.7053683512716,448.1426730387664,707.3939391121079,809.0211378682071,1013.366634472303,2232.857614802746,2787.279459993142,4689.438532127613,270.7115868723324,1.209246937957908,3232.430717004348,1535.926079107527,3507.847462368369</MDI>
      <MDI key="STATISTICS_EXCLUDEDVALUES"></MDI>
      <MDI key="STATISTICS_MAXIMUM">1006</MDI>
      <MDI key="STATISTICS_MEAN">829.0302734375</MDI>
      <MDI key="STATISTICS_MEDIAN">827.000000</MDI>
      <MDI key="STATISTICS_MINIMUM">779</MDI>
      <MDI key="STATISTICS_SKIPFACTORX">1</MDI>
      <MDI key="STATISTICS_SKIPFACTORY">1</MDI>
      <MDI key="STATISTICS_STDDEV">21.169380553969</MDI>
    </Metadata>
  </PAMRasterBand>
  <PAMRasterBand band="3">
    <Histograms>
      <HistItem>
        <HistMin>-0.5</HistMin>
        <HistMax>888.5</HistMax>
        <BucketCount>889</BucketCount>
        <IncludeOutOfRange>1</IncludeOutOfRange>
        <Approximate>0</Approximate>
        <HistCounts>0|0|0|0|0|0|0|0|0|0|0|0|0|0|0|0|0|0|0|0|0|0|0|0|0|0|0|0|0|0|0|0|0|0|0|0|0|0|0|0|0|0|0|0|0|0|0|0|0|0|0|0|0|0|0|0|0|0|0|0|0|0|0|0|0|0|0|0|0|0|0|0|0|0|0|0|0|0|0|0|0|0|0|0|0|0|0|0|0|0|0|0|0|0|0|0|0|0|0|0|0|0|0|0|0|0|0|0|0|0|0|0|0|0|0|0|0|0|0|0|0|0|0|0|0|0|0|0|0|0|0|0|0|0|0|0|0|0|0|0|0|0|0|0|0|0|0|0|0|0|0|0|0|0|0|0|0|0|0|0|0|0|0|0|0|0|0|0|0|0|0|0|0|0|0|0|0|0|0|0|0|0|0|0|0|0|0|0|0|0|0|0|0|0|0|0|0|0|0|0|0|0|0|0|0|0|0|0|0|0|0|0|0|0|0|0|0|0|0|0|0|0|0|0|0|0|0|0|0|0|0|0|0|0|0|0|0|0|0|0|0|0|0|0|0|0|0|0|0|0|0|0|0|0|0|0|0|0|0|0|0|0|0|0|0|0|0|0|0|0|0|0|0|0|0|0|0|0|0|0|0|0|0|0|0|0|0|0|0|0|0|0|0|0|0|0|0|0|0|0|0|0|0|0|0|0|0|0|0|0|0|0|0|0|0|0|0|0|0|0|0|0|0|0|0|0|0|0|0|0|0|0|0|0|0|0|0|0|0|0|0|0|0|0|0|0|0|0|0|0|0|0|0|0|0|0|0|0|0|0|0|0|0|0|0|0|0|0|0|0|0|0|0|0|0|0|0|0|0|0|0|0|0|0|0|0|0|0|0|0|0|0|0|0|0|0|0|0|0|0|0|0|0|0|0|0|0|0|0|0|0|0|0|0|0|0|0|0|0|0|0|0|0|0|0|0|0|0|0|0|0|0|0|0|0|0|0|0|0|0|0|0|0|0|0|0|0|0|0|0|0|0|0|0|0|0|0|0|0|0|0|0|0|0|0|0|0|0|0|0|0|0|0|0|0|0|0|0|0|0|0|0|0|0|0|0|0|0|0|0|0|0|0|0|0|0|0|0|0|0|0|0|0|0|0|0|0|0|0|0|0|0|0|0|0|0|0|0|0|0|0|0|0|1|0|0|0|1|1|0|0|2|4|1|1|2|0|2|4|3|2|3|1|4|8|5|3|5|6|6|4|6|5|9|6|9|8|13|11|8|15|19|13|18|12|15|23|27|24|28|22|17|25|23|33|28|27|31|41|37|49|35|43|43|41|46|50|45|39|54|51|36|56|48|35|42|45|37|43|37|45|30|60|34|42|36|41|40|36|45|32|39|39|39|32|34|48|44|44|46|35|31|36|32|45|31|31|41|28|43|40|34|40|25|39|45|44|44|31|34|40|31|34|37|39|37|33|28|30|34|25|21|24|15|23|25|22|17|18|28|20|27|14|14|15|10|19|15|19|13|9|19|12|15|8|18|8|14|10|15|12|19|12|9|5|4|5|6|6|5|7|0|4|7|5|0|6|3|1|4|2|5|1|5|0|1|1|4|2|3|2|1|2|0|1|3|0|2|0|2|1|4|0|0|0|1|2|1|0|0|0|1|1|2|0|1|3|0|0|0|0|0|0|0|0|0|0|1|1|0|0|2|0|0|0|2|0|1|0|1|0|0|0|0|0|0|0|0|1|0|0|0|0|0|0|0|0|1|1|0|1|0|2|1|0|1|0|1|0|0|0|0|1|1|2|0|0|1|0|0|0|0|0|0|0|0|0|0|1|0|0|0|0|0|1|0|1|0|0|0|0|1|2|0|0|0|1|0|0|0|0|0|1|0|0|0|0|0|0|1|0|0|0|0|0|0|0|0|0|0|0|0|1|0|0|0|0|0|0|0|0|0|0|0|0|1|0|0|0|0|0|0|1|0|0|0|0|0|0|0|0|0|0|0|0|0|0|0|1</HistCounts>
      </HistItem>
    </Histograms>
    <Metadata>
      <MDI key="STATISTICS_COUNT">4096.000000</MDI>
      <MDI key="STATISTICS_COVARIANCES">225.7128897307203,707.3939391121079,1527.512729832026,1498.620339865222,2100.397913745331,5050.370346661782,6484.371686245542,10895.78244953824,724.5868368556211,5.704201066944792,6692.33875170512,3051.581764811807,8158.090980389969</MDI>
      <MDI key="STATISTICS_EXCLUDEDVALUES"></MDI>
      <MDI key="STATISTICS_MAXIMUM">888</MDI>
      <MDI key="STATISTICS_MEAN">616.99047851563</MDI>
      <MDI key="STATISTICS_MEDIAN">613.000000</MDI>
      <MDI key="STATISTICS_MINIMUM">523</MDI>
      <MDI key="STATISTICS_SKIPFACTORX">1</MDI>
      <MDI key="STATISTICS_SKIPFACTORY">1</MDI>
      <MDI key="STATISTICS_STDDEV">39.08340734675</MDI>
    </Metadata>
  </PAMRasterBand>
  <PAMRasterBand band="4">
    <Histograms>
      <HistItem>
        <HistMin>-0.5</HistMin>
        <HistMax>838.5</HistMax>
        <BucketCount>839</BucketCount>
        <IncludeOutOfRange>1</IncludeOutOfRange>
        <Approximate>0</Approximate>
        <HistCounts>0|0|0|0|0|0|0|0|0|0|0|0|0|0|0|0|0|0|0|0|0|0|0|0|0|0|0|0|0|0|0|0|0|0|0|0|0|0|0|0|0|0|0|0|0|0|0|0|0|0|0|0|0|0|0|0|0|0|0|0|0|0|0|0|0|0|0|0|0|0|0|0|0|0|0|0|0|0|0|0|0|0|0|0|0|0|0|0|0|0|0|0|0|0|0|0|0|0|0|0|0|0|0|0|0|0|0|0|0|0|0|0|0|0|0|0|0|0|0|0|0|0|0|0|0|0|0|0|0|0|0|0|0|0|0|0|0|0|0|0|0|0|0|0|0|0|0|0|0|0|0|0|0|0|0|0|0|0|0|0|0|0|0|0|0|0|0|0|0|0|0|0|0|0|0|0|0|0|0|0|0|0|0|0|0|0|0|0|0|0|0|0|0|0|0|0|0|0|0|0|0|0|0|0|0|0|0|0|0|0|0|0|0|0|0|0|0|0|0|0|0|0|0|0|0|0|0|0|0|0|0|0|0|0|0|0|0|0|0|0|0|0|0|0|0|0|0|0|0|0|0|0|0|0|0|0|0|0|0|0|0|0|0|0|0|0|0|0|0|0|0|0|0|0|0|0|0|0|0|0|0|0|0|0|0|0|0|0|0|0|0|0|0|0|0|0|0|0|0|0|0|0|0|0|0|0|0|0|0|0|0|0|0|0|0|0|0|1|0|1|0|1|0|0|0|2|4|5|3|4|5|2|5|5|8|6|8|12|10|13|17|20|17|15|25|18|20|22|35|29|41|56|35|53|51|39|60|79|57|50|47|63|61|59|71|60|52|46|34|58|49|52|58|25|36|56|46|41|47|39|31|36|35|45|47|32|45|33|47|44|33|40|44|47|45|43|32|35|40|47|37|38|35|40|44|42|41|35|36|39|34|46|48|26|34|30|22|37|28|29|40|25|15|32|31|28|22|28|17|14|21|18|20|21|13|17|18|13|17|13|19|13|12|8|13|13|13|5|5|5|7|8|5|5|3|3|4|8|8|5|3|4|7|6|6|6|2|3|2|2|1|2|5|3|1|1|7|2|2|2|2|3|1|0|3|0|3|2|2|2|0|1|1|1|4|2|0|0|1|0|2|0|0|2|0|0|0|3|2|0|0|1|0|0|0|0|0|2|0|1|1|0|0|0|1|2|1|1|0|0|0|1|0|0|0|0|1|0|0|0|0|0|0|0|0|0|0|0|0|0|0|1|0|1|0|0|0|1|0|0|0|0|0|0|0|0|0|0|1|0|0|0|0|0|1|0|1|1|0|0|0|1|0|0|1|0|0|0|0|0|0|0|0|0|0|0|1|0|0|1|0|0|0|0|0|0|0|0|0|0|0|0|0|0|0|0|0|0|0|0|0|0|0|0|0|0|1|0|0|2|0|0|1|0|0|0|2|0|0|0|0|0|0|0|0|0|0|0|0|0|0|0|0|0|0|0|1|0|1|0|0|0|0|0|1|0|0|1|1|1|0|0|0|0|0|0|0|0|0|0|0|0|0|0|0|0|0|0|0|1|0|0|0|0|0|0|0|0|0|0|0|0|0|0|0|0|0|0|0|0|0|1|0|0|0|0|0|0|0|1|1|1|0|0|0|0|0|0|0|0|0|0|0|0|0|0|0|0|0|1|0|0|0|0|0|1|0|0|0|1|0|1|0|1|1|0|0|1|0|0|0|0|0|0|0|2|0|0|0|0|0|0|0|0|0|0|0|0|0|0|0|0|0|0|0|0|0|0|0|0|1|0|0|0|0|0|0|0|0|0|0|0|0|0|0|0|0|0|0|0|0|0|0|0|0|0|0|0|0|0|0|0|0|0|0|0|0|0|0|0|0|0|0|0|0|0|0|0|1</HistCounts>
      </HistItem>
    </Histograms>
    <Metadata>
      <MDI key="STATISTICS_COUNT">4096.000000</MDI>
      <MDI key="STATISTICS_COVARIANCES">262.6004166785953,809.0211378682071,1498.620339865222,1855.354078370626,2365.28862817412,4783.234595412199,5967.49376776655,9611.597336214147,736.0653675046769,5.768862859146243,7642.572984334446,3663.343040710367,7702.413214297659</MDI>
      <MDI key="STATISTICS_EXCLUDEDVALUES"></MDI>
      <MDI key="STATISTICS_MAXIMUM">838</MDI>
      <MDI key="STATISTICS_MEAN">391.36645507813</MDI>
      <MDI key="STATISTICS_MEDIAN">385.000000</MDI>
      <MDI key="STATISTICS_MINIMUM">317</MDI>
      <MDI key="STATISTICS_SKIPFACTORX">1</MDI>
      <MDI key="STATISTICS_SKIPFACTORY">1</MDI>
      <MDI key="STATISTICS_STDDEV">43.073821265017</MDI>
    </Metadata>
  </PAMRasterBand>
  <PAMRasterBand band="5">
    <Histograms>
      <HistItem>
        <HistMin>-0.5</HistMin>
        <HistMax>876.5</HistMax>
        <BucketCount>877</BucketCount>
        <IncludeOutOfRange>1</IncludeOutOfRange>
        <Approximate>0</Approximate>
        <HistCounts>0|0|0|0|0|0|0|0|0|0|0|0|0|0|0|0|0|0|0|0|0|0|0|0|0|0|0|0|0|0|0|0|0|0|0|0|0|0|0|0|0|0|0|0|0|0|0|0|0|0|0|0|0|0|0|0|0|0|0|0|0|0|0|0|0|0|0|0|0|0|0|0|0|0|0|0|0|0|0|0|0|0|0|0|0|0|0|0|0|0|0|0|0|0|0|0|0|0|0|0|0|0|0|0|0|0|0|0|0|0|0|0|0|0|0|0|0|0|0|0|0|0|0|0|0|0|0|0|0|0|0|0|0|0|0|0|0|0|0|0|0|0|0|0|0|0|0|0|0|0|0|0|0|0|0|0|0|0|0|0|0|0|0|0|0|0|0|0|0|0|0|0|0|0|0|0|0|0|0|0|0|0|0|0|0|0|0|0|0|0|0|0|0|0|0|0|0|0|0|0|0|0|0|0|0|0|0|0|0|0|0|0|0|0|0|0|0|0|0|0|0|0|0|0|0|0|0|0|0|0|0|0|0|0|0|0|0|0|0|0|0|0|0|0|0|0|0|0|0|0|0|0|0|0|0|0|0|0|0|0|0|0|0|0|0|0|0|0|0|0|0|0|0|0|0|0|0|0|0|0|0|0|0|0|0|0|0|0|0|0|0|0|0|0|0|0|0|0|0|0|0|0|0|0|0|0|0|0|0|0|0|0|0|0|0|0|0|0|0|0|0|0|0|0|0|0|0|0|0|0|0|0|0|0|0|0|0|0|0|0|0|0|0|0|0|0|0|0|0|0|0|0|0|0|0|0|0|0|0|0|0|0|0|0|0|0|0|0|0|0|0|0|0|0|0|0|0|0|0|0|0|0|0|0|0|0|0|0|0|1|1|0|0|0|0|0|0|0|1|0|1|2|0|2|4|0|1|5|3|4|5|2|5|2|4|3|2|8|6|5|5|10|7|10|7|9|12|8|11|10|8|15|20|20|11|7|14|18|13|13|22|23|21|20|22|25|22|24|25|26|24|22|21|22|23|32|21|22|24|23|17|19|26|26|30|22|23|24|28|25|20|24|41|17|27|23|22|21|25|30|23|25|25|34|18|24|26|13|18|16|17|27|15|13|16|19|13|13|20|18|18|14|16|25|25|17|24|22|13|17|21|21|22|16|14|22|20|19|12|21|11|18|19|11|12|20|21|18|23|24|15|15|25|20|26|12|15|21|24|25|27|26|29|17|22|26|21|30|25|18|21|26|25|18|26|20|28|35|28|22|20|28|21|36|23|27|22|25|30|26|27|22|22|22|17|16|19|16|22|19|17|20|7|15|21|11|19|18|12|17|10|14|20|12|14|19|6|10|15|17|13|14|16|6|7|7|16|12|8|4|12|8|12|7|12|7|7|3|11|11|10|10|2|5|10|8|6|4|6|5|4|1|0|3|9|4|7|3|7|3|3|4|2|3|2|7|1|4|1|3|0|6|5|5|3|0|1|1|1|2|3|2|4|1|2|3|0|2|2|4|1|1|2|1|2|1|1|1|0|1|4|0|0|1|0|0|0|1|1|1|1|1|0|0|0|0|2|1|2|0|0|1|0|0|1|0|1|0|1|0|0|0|0|1|0|0|1|0|0|0|0|0|0|0|1|2|1|0|0|1|0|0|0|1|0|0|0|2|0|1|0|0|0|0|0|2|0|0|0|1|0|2|0|1|0|1|0|0|0|0|1|1|1|0|0|0|0|0|1|0|0|0|2|0|0|0|0|0|0|1|0|0|0|0|0|1|0|1|1|1|1|0|0|0|0|0|0|0|0|0|2|0|0|0|1|0|0|1|1|0|2|0|1|0|0|1|0|0|0|1|0|0|0|1|0|0|0|0|0|0|0|1|1|0|0|0|1|0|0|0|0|0|0|0|0|0|0|1|0|0|0|0|0|0|0|1|0|0|0|0|0|0|0|0|0|0|1|0|0|1|0|0|0|0|0|0|1</HistCounts>
      </HistItem>
    </Histograms>
    <Metadata>
      <MDI key="STATISTICS_COUNT">4096.000000</MDI>
      <MDI key="STATISTICS_COVARIANCES">511.3031942178945,1013.366634472303,2100.397913745331,2365.28862817412,4402.41398898952,10268.60349302932,13372.01401683172,16542.99127127213,1842.064488717658,14.55082423544338,14621.27666760866,6584.597977418648,17043.01461821064</MDI>
      <MDI key="STATISTICS_EXCLUDEDVALUES"></MDI>
      <MDI key="STATISTICS_MAXIMUM">876</MDI>
      <MDI key="STATISTICS_MEAN">524.03735351563</MDI>
      <MDI key="STATISTICS_MEDIAN">521.000000</MDI>
      <MDI key="STATISTICS_MINIMUM">389</MDI>
      <MDI key="STATISTICS_SKIPFACTORX">1</MDI>
      <MDI key="STATISTICS_SKIPFACTORY">1</MDI>
      <MDI key="STATISTICS_STDDEV">66.35068943869</MDI>
    </Metadata>
  </PAMRasterBand>
  <PAMRasterBand band="6">
    <Histograms>
      <HistItem>
        <HistMin>-0.5</HistMin>
        <HistMax>2123.5</HistMax>
        <BucketCount>2124</BucketCount>
        <IncludeOutOfRange>1</IncludeOutOfRange>
        <Approximate>0</Approximate>
        <HistCounts>0|0|0|0|0|0|0|0|0|0|0|0|0|0|0|0|0|0|0|0|0|0|0|0|0|0|0|0|0|0|0|0|0|0|0|0|0|0|0|0|0|0|0|0|0|0|0|0|0|0|0|0|0|0|0|0|0|0|0|0|0|0|0|0|0|0|0|0|0|0|0|0|0|0|0|0|0|0|0|0|0|0|0|0|0|0|0|0|0|0|0|0|0|0|0|0|0|0|0|0|0|0|0|0|0|0|0|0|0|0|0|0|0|0|0|0|0|0|0|0|0|0|0|0|0|0|0|0|0|0|0|0|0|0|0|0|0|0|0|0|0|0|0|0|0|0|0|0|0|0|0|0|0|0|0|0|0|0|0|0|0|0|0|0|0|0|0|0|0|0|0|0|0|0|0|0|0|0|0|0|0|0|0|0|0|0|0|0|0|0|0|0|0|0|0|0|0|0|0|0|0|0|0|0|0|0|0|0|0|0|0|0|0|0|0|0|0|0|0|0|0|0|0|0|0|0|0|0|0|0|0|0|0|0|0|0|0|0|0|0|0|0|0|0|0|0|0|0|0|0|0|0|0|0|0|0|0|0|0|0|0|0|0|0|0|0|0|0|0|0|0|0|0|0|0|0|0|0|0|0|0|0|0|0|0|0|0|0|0|0|0|0|0|0|0|0|0|0|0|0|0|0|0|0|0|0|0|0|0|0|0|0|0|0|0|0|0|0|0|0|0|0|0|0|0|0|0|0|0|0|0|0|0|0|0|0|0|0|0|0|0|0|0|0|0|0|0|0|0|0|0|0|0|0|0|0|0|0|0|0|0|0|0|0|0|0|0|0|0|0|0|0|0|0|0|0|0|0|0|0|0|0|0|0|0|0|0|0|0|0|0|0|0|0|0|0|0|0|0|0|0|0|0|0|0|0|0|0|0|0|0|0|0|0|0|0|0|0|0|0|0|0|0|0|0|0|0|0|0|0|0|0|0|0|0|0|0|0|0|0|0|0|0|0|0|0|0|0|0|0|0|0|0|0|0|0|0|0|0|0|0|0|0|0|0|0|0|0|0|0|0|0|0|0|0|0|0|0|0|0|0|0|0|0|0|0|0|0|0|0|0|0|0|0|0|0|0|0|0|0|0|0|0|0|0|0|0|0|0|0|0|0|0|0|0|0|0|0|0|0|0|0|0|0|0|0|0|0|0|0|0|0|0|0|0|0|0|0|0|0|0|0|0|0|0|0|0|0|0|0|0|0|0|0|0|0|0|0|0|0|0|0|0|0|0|0|0|0|0|0|0|0|0|0|0|0|0|0|0|0|0|0|0|0|0|0|0|0|0|0|0|0|0|0|0|0|0|0|0|0|0|0|0|0|0|0|0|0|0|0|0|0|0|0|0|0|0|0|0|0|0|0|0|0|0|0|0|0|0|0|0|0|0|0|0|0|0|0|0|0|0|0|0|0|0|0|0|0|0|0|0|0|0|0|0|0|0|0|0|0|0|0|0|0|0|0|0|0|0|0|0|0|0|0|0|0|0|0|0|0|0|0|0|0|0|0|0|0|0|0|0|0|0|0|0|0|0|0|0|0|0|0|0|0|0|0|0|0|0|0|0|0|0|0|0|0|0|0|0|0|0|0|0|0|0|0|0|0|0|0|0|0|0|0|0|0|0|0|0|0|0|0|0|0|0|0|0|0|0|0|0|0|0|0|0|0|0|0|0|0|0|0|0|0|0|0|0|0|0|0|0|0|0|0|0|0|0|0|0|0|0|0|0|0|0|0|0|0|0|0|0|0|0|0|0|0|0|0|0|0|0|0|0|0|0|0|0|0|1|0|0|0|0|0|0|0|0|0|0|0|0|0|0|0|0|0|0|1|0|0|0|0|0|1|0|0|0|0|0|1|0|0|0|0|0|0|1|0|0|0|0|0|0|1|0|0|0|0|2|0|0|0|1|0|0|0|2|0|1|0|0|0|0|0|2|0|1|0|0|0|1|0|0|0|0|0|0|0|0|0|0|0|0|0|1|0|1|0|0|1|0|1|0|0|0|1|1|0|2|0|0|2|0|0|1|1|0|1|2|0|0|0|1|3|0|0|2|0|4|2|0|2|1|2|1|4|0|0|3|0|1|2|2|3|0|0|0|3|0|1|0|1|0|0|0|1|1|1|2|0|2|1|3|4|0|4|2|2|4|4|1|0|2|4|1|3|5|3|3|1|8|2|4|3|4|5|1|0|3|3|1|3|4|1|2|0|0|8|5|1|6|3|0|3|5|1|3|4|2|1|2|5|3|4|3|4|3|2|3|0|2|3|3|2|2|5|0|5|6|4|3|0|2|3|3|2|4|4|5|6|4|3|3|4|5|2|4|13|4|5|4|4|4|10|1|5|3|5|6|7|3|3|6|6|7|9|6|3|1|5|10|7|6|4|4|5|5|4|3|7|4|4|6|10|4|3|5|3|4|5|4|0|5|2|2|4|4|10|7|11|3|4|6|6|6|9|6|6|10|3|5|8|4|7|5|9|6|2|7|5|6|6|3|9|6|8|2|7|6|6|3|9|10|5|8|6|11|5|8|5|10|6|9|3|4|8|10|4|5|3|8|9|7|8|4|7|7|5|9|7|8|2|9|1|5|5|9|5|8|14|8|2|9|1|5|9|15|4|8|8|8|12|11|2|6|5|6|5|11|6|6|9|8|14|4|12|11|13|6|11|9|7|4|5|7|6|10|8|8|13|9|3|7|14|7|6|18|9|7|6|7|13|9|10|7|12|8|13|13|3|6|9|12|11|11|9|14|13|15|14|4|6|14|16|12|9|11|9|13|11|16|9|8|7|9|9|15|12|8|9|8|5|12|6|10|11|14|12|6|12|12|9|9|14|7|10|9|9|12|9|8|7|5|10|7|15|12|3|12|7|13|10|9|11|7|10|12|11|8|10|12|8|11|16|17|10|7|15|9|7|11|5|14|13|10|3|10|11|6|9|8|8|2|14|11|12|6|6|5|14|5|10|9|12|7|3|11|3|8|4|4|8|6|12|5|5|6|9|12|10|7|9|8|8|11|6|9|7|6|3|8|7|8|4|11|10|7|11|7|14|7|8|3|13|8|8|6|7|5|3|3|1|5|7|8|8|7|5|9|4|7|7|3|12|7|8|5|9|2|13|5|8|6|8|9|6|4|7|12|6|7|7|8|4|5|11|10|6|4|9|4|9|4|11|5|3|4|2|5|6|7|3|8|9|5|4|7|5|2|3|3|3|9|6|4|1|8|6|7|6|4|8|3|7|5|8|6|5|3|5|7|4|3|5|4|6|3|4|10|2|4|9|7|7|5|1|6|4|3|7|10|3|4|3|5|5|2|6|3|1|5|6|4|3|3|3|2|2|1|5|7|8|2|1|1|1|4|0|3|3|1|2|5|3|3|4|1|4|4|3|5|4|5|2|5|4|5|3|4|4|1|4|2|1|1|2|1|1|1|5|2|5|2|0|1|2|3|1|1|4|3|3|1|2|1|3|3|4|5|0|2|1|0|0|6|1|2|1|2|4|3|0|2|4|2|2|1|2|2|4|1|1|2|3|1|1|0|2|1|2|2|2|3|2|1|5|2|3|3|1|1|0|3|0|0|1|1|2|2|0|0|1|1|0|2|1|1|3|4|2|4|1|1|1|1|3|0|2|1|0|3|0|4|0|2|2|2|0|0|6|2|0|1|3|2|2|4|2|1|0|1|3|1|1|4|1|0|2|3|0|0|0|3|1|0|2|3|0|1|1|1|2|0|0|1|4|0|7|2|0|1|1|0|4|1|2|2|1|0|0|2|1|1|0|0|0|1|2|0|3|2|2|1|1|3|1|2|3|1|1|3|1|2|3|0|1|1|3|1|2|1|1|3|2|2|0|0|1|1|1|0|1|0|1|2|0|1|2|0|2|2|0|2|1|0|1|2|3|1|0|2|1|1|0|0|2|0|1|0|2|0|0|1|0|1|0|2|2|0|1|0|0|1|0|0|2|3|2|0|0|2|0|1|1|0|0|1|1|2|0|0|0|0|1|0|1|0|2|2|0|1|0|1|0|0|0|0|0|0|0|1|0|0|0|0|1|2|0|0|1|1|0|0|1|0|0|1|0|1|0|1|0|1|1|0|0|1|0|1|0|0|0|0|0|1|0|1|0|0|0|0|0|0|0|0|0|0|0|0|0|0|0|0|0|0|0|0|1|0|0|0|0|0|0|0|0|0|0|0|0|0|0|0|0|0|0|0|0|0|0|0|0|0|0|0|0|1|1|0|0|0|0|0|0|0|0|0|0|0|0|0|0|0|1|0|0|0|0|0|0|0|0|0|0|0|0|0|0|0|0|0|0|0|0|0|0|1|0|0|0|0|0|0|0|0|0|0|0|0|0|1|0|0|0|0|0|0|0|0|0|0|1|0|0|0|0|0|0|0|0|1|0|0|0|0|0|0|0|0|0|0|0|0|0|0|0|0|0|0|0|0|1|0|0|0|0|0|0|0|0|0|0|0|0|0|0|0|0|0|0|0|0|0|0|0|0|0|0|0|0|0|0|0|0|1|0|0|1|0|0|0|0|0|0|0|0|0|0|0|0|0|0|0|1|0|0|0|0|0|0|0|0|0|0|0|0|1|0|0|0|0|0|0|0|0|0|0|0|0|0|0|0|0|0|1|0|0|0|0|0|0|0|0|0|0|0|0|0|0|0|0|0|0|0|0|0|0|0|0|0|0|0|0|0|0|0|0|0|0|0|1|0|0|0|0|0|0|0|0|0|0|0|0|1</HistCounts>
      </HistItem>
    </Histograms>
    <Metadata>
      <MDI key="STATISTICS_COUNT">4096.000000</MDI>
      <MDI key="STATISTICS_COVARIANCES">1216.119111232694,2232.857614802746,5050.370346661782,4783.234595412199,10268.60349302932,35318.42165983431,48111.15721571178,58257.82087578211,5906.66439964655,43.64193870907697,33484.42532391117,13722.78396487949,58578.06473852212</MDI>
      <MDI key="STATISTICS_EXCLUDEDVALUES"></MDI>
      <MDI key="STATISTICS_MAXIMUM">2123</MDI>
      <MDI key="STATISTICS_MEAN">1294.1940917969</MDI>
      <MDI key="STATISTICS_MEDIAN">1279.000000</MDI>
      <MDI key="STATISTICS_MINIMUM">808</MDI>
      <MDI key="STATISTICS_SKIPFACTORX">1</MDI>
      <MDI key="STATISTICS_SKIPFACTORY">1</MDI>
      <MDI key="STATISTICS_STDDEV">187.93196018728</MDI>
    </Metadata>
  </PAMRasterBand>
  <PAMRasterBand band="7">
    <Histograms>
      <HistItem>
        <HistMin>-0.5</HistMin>
        <HistMax>2897.5</HistMax>
        <BucketCount>2898</BucketCount>
        <IncludeOutOfRange>1</IncludeOutOfRange>
        <Approximate>0</Approximate>
        <HistCounts>0|0|0|0|0|0|0|0|0|0|0|0|0|0|0|0|0|0|0|0|0|0|0|0|0|0|0|0|0|0|0|0|0|0|0|0|0|0|0|0|0|0|0|0|0|0|0|0|0|0|0|0|0|0|0|0|0|0|0|0|0|0|0|0|0|0|0|0|0|0|0|0|0|0|0|0|0|0|0|0|0|0|0|0|0|0|0|0|0|0|0|0|0|0|0|0|0|0|0|0|0|0|0|0|0|0|0|0|0|0|0|0|0|0|0|0|0|0|0|0|0|0|0|0|0|0|0|0|0|0|0|0|0|0|0|0|0|0|0|0|0|0|0|0|0|0|0|0|0|0|0|0|0|0|0|0|0|0|0|0|0|0|0|0|0|0|0|0|0|0|0|0|0|0|0|0|0|0|0|0|0|0|0|0|0|0|0|0|0|0|0|0|0|0|0|0|0|0|0|0|0|0|0|0|0|0|0|0|0|0|0|0|0|0|0|0|0|0|0|0|0|0|0|0|0|0|0|0|0|0|0|0|0|0|0|0|0|0|0|0|0|0|0|0|0|0|0|0|0|0|0|0|0|0|0|0|0|0|0|0|0|0|0|0|0|0|0|0|0|0|0|0|0|0|0|0|0|0|0|0|0|0|0|0|0|0|0|0|0|0|0|0|0|0|0|0|0|0|0|0|0|0|0|0|0|0|0|0|0|0|0|0|0|0|0|0|0|0|0|0|0|0|0|0|0|0|0|0|0|0|0|0|0|0|0|0|0|0|0|0|0|0|0|0|0|0|0|0|0|0|0|0|0|0|0|0|0|0|0|0|0|0|0|0|0|0|0|0|0|0|0|0|0|0|0|0|0|0|0|0|0|0|0|0|0|0|0|0|0|0|0|0|0|0|0|0|0|0|0|0|0|0|0|0|0|0|0|0|0|0|0|0|0|0|0|0|0|0|0|0|0|0|0|0|0|0|0|0|0|0|0|0|0|0|0|0|0|0|0|0|0|0|0|0|0|0|0|0|0|0|0|0|0|0|0|0|0|0|0|0|0|0|0|0|0|0|0|0|0|0|0|0|0|0|0|0|0|0|0|0|0|0|0|0|0|0|0|0|0|0|0|0|0|0|0|0|0|0|0|0|0|0|0|0|0|0|0|0|0|0|0|0|0|0|0|0|0|0|0|0|0|0|0|0|0|0|0|0|0|0|0|0|0|0|0|0|0|0|0|0|0|0|0|0|0|0|0|0|0|0|0|0|0|0|0|0|0|0|0|0|0|0|0|0|0|0|0|0|0|0|0|0|0|0|0|0|0|0|0|0|0|0|0|0|0|0|0|0|0|0|0|0|0|0|0|0|0|0|0|0|0|0|0|0|0|0|0|0|0|0|0|0|0|0|0|0|0|0|0|0|0|0|0|0|0|0|0|0|0|0|0|0|0|0|0|0|0|0|0|0|0|0|0|0|0|0|0|0|0|0|0|0|0|0|0|0|0|0|0|0|0|0|0|0|0|0|0|0|0|0|0|0|0|0|0|0|0|0|0|0|0|0|0|0|0|0|0|0|0|0|0|0|0|0|0|0|0|0|0|0|0|0|0|0|0|0|0|0|0|0|0|0|0|0|0|0|0|0|0|0|0|0|0|0|0|0|0|0|0|0|0|0|0|0|0|0|0|0|0|0|0|0|0|0|0|0|0|0|0|0|0|0|0|0|0|0|0|0|0|0|0|0|0|0|0|0|0|0|0|0|0|0|0|0|0|0|0|0|0|0|0|0|0|0|0|0|0|0|0|0|0|0|0|0|0|0|0|0|0|0|0|0|0|0|0|0|0|0|0|0|0|0|0|0|0|0|0|0|0|0|0|0|0|0|0|0|0|0|0|0|0|0|0|0|0|0|0|0|0|0|0|0|0|0|0|0|0|0|0|0|0|0|0|0|0|0|0|0|0|0|0|0|0|0|0|0|0|0|0|0|0|0|0|0|0|0|0|0|0|0|0|0|0|0|0|0|0|0|0|0|0|0|0|0|0|0|0|0|0|0|0|0|0|0|0|0|0|0|0|0|0|0|0|0|0|0|0|0|0|0|0|0|0|0|0|0|0|0|0|0|0|0|0|0|0|0|0|0|0|0|0|0|0|0|0|0|0|0|0|0|0|0|0|0|0|0|0|0|0|0|0|0|0|0|0|0|0|0|0|0|0|0|0|0|0|0|0|0|0|0|0|0|0|0|0|0|0|0|0|0|0|0|0|0|0|0|0|0|0|0|0|0|0|0|0|0|0|0|0|0|0|0|0|0|1|0|0|0|0|0|0|2|0|0|0|0|0|1|0|0|0|0|0|0|0|0|0|0|0|0|0|0|1|0|0|0|0|0|1|0|0|0|0|0|0|1|0|0|0|0|0|0|0|0|0|0|0|0|0|0|0|0|0|1|0|0|2|1|0|1|0|0|0|0|0|0|0|0|0|1|0|0|0|0|0|0|0|0|0|0|0|0|1|0|0|0|1|0|0|0|0|0|0|0|0|0|0|0|0|0|0|0|0|0|0|0|0|0|2|0|0|1|0|1|0|1|0|1|0|1|1|1|2|1|2|1|0|1|1|0|0|1|1|0|0|0|1|0|0|0|0|0|0|0|0|2|0|2|0|0|0|0|0|0|0|0|1|1|1|0|0|0|0|2|0|3|0|0|0|1|0|0|1|0|1|2|0|0|0|1|0|1|1|0|1|0|0|1|2|0|1|2|0|1|0|0|1|0|0|2|0|2|4|1|2|3|0|1|0|1|0|1|0|2|1|2|2|4|3|0|3|1|2|0|2|2|0|1|1|3|1|0|1|3|5|0|2|3|1|1|2|1|6|4|1|2|2|2|2|1|2|4|0|1|2|4|3|1|3|3|0|4|1|1|2|3|1|6|1|1|0|3|2|2|0|0|5|5|1|2|0|2|3|2|2|5|1|1|3|4|3|1|1|4|5|2|2|0|0|1|1|2|0|2|1|3|2|0|3|4|5|5|3|0|3|1|2|2|5|3|4|3|3|4|5|1|2|1|2|2|1|2|5|1|1|4|4|0|3|2|3|6|5|2|5|4|0|3|3|3|1|4|3|3|4|5|4|1|3|4|6|4|4|4|5|2|4|5|4|9|4|1|7|2|4|6|3|3|1|4|4|6|4|4|5|6|4|4|3|6|4|5|2|4|2|2|2|1|5|3|3|5|4|7|4|6|3|3|4|7|4|3|1|7|3|1|5|4|4|6|3|4|6|1|7|7|7|5|5|4|7|4|9|6|4|3|4|5|5|5|6|0|3|8|8|2|5|0|6|6|2|9|3|9|3|5|2|4|7|3|4|5|2|6|9|6|10|8|2|7|3|9|3|2|4|4|4|6|4|7|4|3|3|6|3|5|6|5|4|5|7|6|11|5|5|10|6|4|8|10|3|4|5|5|8|8|5|5|6|4|4|10|5|8|2|7|11|8|6|6|10|8|5|8|6|9|13|6|4|3|2|8|2|7|4|9|8|10|9|3|9|9|6|7|4|8|6|5|5|5|4|5|9|6|5|11|3|6|8|4|13|6|6|5|5|3|7|7|4|6|3|7|7|5|8|5|10|10|8|12|11|7|7|4|9|5|7|5|8|9|3|3|8|8|7|7|8|5|8|12|5|12|8|9|2|7|6|4|7|7|5|5|4|7|4|7|14|5|5|8|2|7|10|3|4|5|4|13|9|6|6|10|8|9|4|6|8|6|7|14|13|9|5|15|3|6|13|8|13|8|11|7|6|8|14|6|11|4|6|12|5|11|7|4|5|7|15|5|2|9|8|10|11|6|8|7|9|5|4|4|11|10|6|5|5|4|7|9|5|9|9|9|6|13|8|4|5|9|7|9|11|6|10|7|4|8|4|2|4|6|6|9|6|4|4|4|5|6|7|10|6|4|5|5|10|7|3|4|4|6|6|6|10|5|10|3|6|6|3|7|6|2|7|7|3|1|3|3|7|7|3|8|5|7|2|5|1|1|6|4|3|6|6|5|4|6|3|2|4|3|10|8|7|2|6|6|5|7|7|5|9|4|3|5|5|4|1|8|3|3|2|3|3|6|8|6|5|11|3|5|4|3|5|2|6|4|6|9|2|9|7|7|3|3|9|4|4|5|5|3|3|6|8|2|3|3|5|3|5|6|3|3|5|5|6|3|2|6|7|2|4|4|3|5|4|4|7|0|1|5|5|4|2|2|2|4|2|2|4|3|3|8|7|7|1|2|2|5|2|4|3|4|4|7|2|2|6|3|3|4|4|4|6|5|9|5|2|5|3|4|9|6|7|2|6|3|3|1|5|1|0|2|3|6|2|3|2|3|5|3|5|3|1|4|2|3|2|6|3|3|2|3|3|1|5|1|2|5|1|2|0|2|2|3|5|3|4|6|5|0|3|1|1|2|1|1|1|3|1|4|4|2|2|1|2|2|3|5|3|2|2|2|1|1|3|4|1|2|2|6|1|4|3|1|2|2|1|2|2|4|1|0|3|1|2|0|1|2|4|4|3|1|4|5|2|0|0|3|1|2|0|3|1|3|0|2|3|2|0|1|1|1|2|2|1|1|1|6|0|1|0|4|1|1|1|0|1|1|3|1|1|5|3|1|0|0|0|1|3|3|4|2|2|1|2|3|1|2|4|1|1|1|1|4|5|3|0|2|0|0|6|0|0|0|1|1|0|2|1|1|3|1|1|2|2|1|1|0|1|0|1|4|1|1|2|1|3|3|1|2|0|2|1|1|2|4|0|0|2|0|2|0|0|1|0|1|1|3|0|3|1|0|2|5|1|4|1|3|1|0|2|2|0|1|2|1|5|2|2|3|1|2|3|4|0|1|3|1|0|0|1|1|0|1|0|2|1|4|0|1|0|0|1|0|0|1|0|1|0|1|0|2|0|2|1|2|1|0|0|1|1|0|3|0|0|2|0|0|1|3|3|0|0|3|3|2|1|1|0|0|2|0|3|2|2|0|1|0|0|1|2|0|2|0|0|2|3|1|0|2|1|0|0|1|0|1|1|2|0|2|1|3|0|1|0|1|1|0|1|2|0|1|0|1|3|1|1|0|1|0|1|0|0|4|0|3|1|1|2|0|1|3|2|1|0|1|0|0|0|1|3|1|0|0|0|0|1|0|0|0|1|1|0|0|1|0|0|0|0|0|2|1|0|1|1|1|0|0|1|0|2|1|0|0|0|0|0|1|0|0|0|0|1|1|0|0|0|1|0|1|0|0|1|0|0|1|0|0|0|0|1|0|0|0|0|0|0|1|1|0|0|0|2|2|1|1|0|1|0|0|0|1|0|0|0|2|0|1|1|0|0|0|0|2|1|1|0|1|0|0|1|0|0|1|1|1|0|0|0|0|0|0|0|0|1|0|0|0|1|1|0|0|0|0|0|0|0|0|0|1|1|1|0|2|1|0|0|1|0|0|0|1|1|1|0|0|0|0|0|0|0|0|0|0|0|0|1|2|0|0|0|1|0|0|0|0|0|0|0|0|1|0|0|0|1|1|0|0|0|0|0|0|0|0|0|0|0|0|0|0|0|0|0|0|0|0|0|0|0|0|0|0|0|1|0|1|1|1|0|1|0|1|0|0|1|0|0|0|0|0|0|0|0|0|0|0|0|0|0|0|1|0|0|0|0|0|0|0|0|0|0|0|0|0|0|0|0|1|0|0|0|0|0|0|0|0|0|0|0|0|0|0|0|0|0|0|0|0|0|0|0|0|0|0|0|0|0|0|0|1|0|0|0|0|0|0|0|0|0|0|0|0|0|0|0|0|0|0|0|1|0|0|0|0|0|0|0|0|0|0|0|0|0|0|0|0|0|0|1|0|0|0|0|0|0|0|0|0|0|0|0|0|0|0|0|0|0|0|1|0|0|0|0|0|0|0|0|0|0|0|0|0|0|0|0|0|0|0|0|0|0|0|0|0|0|0|0|0|0|1|0|0|0|0|0|0|0|0|0|0|0|0|0|0|0|0|0|0|0|0|0|0|0|0|0|0|0|0|0|0|0|0|0|0|0|0|0|0|0|0|0|0|0|0|0|0|1|1|0|0|0|0|0|0|0|0|0|0|0|0|0|0|0|0|0|0|0|0|0|0|0|0|0|0|0|0|0|0|0|0|0|0|0|0|0|0|0|0|0|0|0|0|0|0|0|0|0|0|0|0|0|0|0|0|0|0|0|0|0|0|1|0|0|1|0|0|0|0|0|0|0|0|0|0|0|0|0|0|0|1|0|0|0|0|0|0|1|0|0|0|0|0|0|0|0|0|0|0|0|0|0|0|0|0|0|0|0|0|0|0|0|0|0|0|0|0|0|0|0|0|0|0|0|0|0|0|0|0|0|0|0|0|0|0|0|0|0|0|0|0|0|0|0|0|0|0|0|0|1|0|0|0|0|0|0|0|0|0|0|0|0|0|0|0|0|0|0|0|0|0|0|0|0|0|0|0|0|0|0|0|0|0|0|0|0|0|0|0|0|0|0|0|0|0|0|0|1|1</HistCounts>
      </HistItem>
    </Histograms>
    <Metadata>
      <MDI key="STATISTICS_COUNT">4096.000000</MDI>
      <MDI key="STATISTICS_COVARIANCES">1549.965719317505,2787.279459993142,6484.371686245542,5967.49376776655,13372.01401683172,48111.15721571178,67384.06282408988,80537.81422180231,8214.420450220325,63.55220531421677,43322.67171820145,17417.75211445456,80733.15825594759</MDI>
      <MDI key="STATISTICS_EXCLUDEDVALUES"></MDI>
      <MDI key="STATISTICS_MAXIMUM">2897</MDI>
      <MDI key="STATISTICS_MEAN">1686.2065429687</MDI>
      <MDI key="STATISTICS_MEDIAN">1665.000000</MDI>
      <MDI key="STATISTICS_MINIMUM">1014</MDI>
      <MDI key="STATISTICS_SKIPFACTORX">1</MDI>
      <MDI key="STATISTICS_SKIPFACTORY">1</MDI>
      <MDI key="STATISTICS_STDDEV">259.58440404633</MDI>
    </Metadata>
  </PAMRasterBand>
  <PAMRasterBand band="8">
    <Histograms>
      <HistItem>
        <HistMin>-0.5</HistMin>
        <HistMax>3067.5</HistMax>
        <BucketCount>3068</BucketCount>
        <IncludeOutOfRange>1</IncludeOutOfRange>
        <Approximate>0</Approximate>
        <HistCounts>0|0|0|0|0|0|0|0|0|0|0|0|0|0|0|0|0|0|0|0|0|0|0|0|0|0|0|0|0|0|0|0|0|0|0|0|0|0|0|0|0|0|0|0|0|0|0|0|0|0|0|0|0|0|0|0|0|0|0|0|0|0|0|0|0|0|0|0|0|0|0|0|0|0|0|0|0|0|0|0|0|0|0|0|0|0|0|0|0|0|0|0|0|0|0|0|0|0|0|0|0|0|0|0|0|0|0|0|0|0|0|0|0|0|0|0|0|0|0|0|0|0|0|0|0|0|0|0|0|0|0|0|0|0|0|0|0|0|0|0|0|0|0|0|0|0|0|0|0|0|0|0|0|0|0|0|0|0|0|0|0|0|0|0|0|0|0|0|0|0|0|0|0|0|0|0|0|0|0|0|0|0|0|0|0|0|0|0|0|0|0|0|0|0|0|0|0|0|0|0|0|0|0|0|0|0|0|0|0|0|0|0|0|0|0|0|0|0|0|0|0|0|0|0|0|0|0|0|0|0|0|0|0|0|0|0|0|0|0|0|0|0|0|0|0|0|0|0|0|0|0|0|0|0|0|0|0|0|0|0|0|0|0|0|0|0|0|0|0|0|0|0|0|0|0|0|0|0|0|0|0|0|0|0|0|0|0|0|0|0|0|0|0|0|0|0|0|0|0|0|0|0|0|0|0|0|0|0|0|0|0|0|0|0|0|0|0|0|0|0|0|0|0|0|0|0|0|0|0|0|0|0|0|0|0|0|0|0|0|0|0|0|0|0|0|0|0|0|0|0|0|0|0|0|0|0|0|0|0|0|0|0|0|0|0|0|0|0|0|0|0|0|0|0|0|0|0|0|0|0|0|0|0|0|0|0|0|0|0|0|0|0|0|0|0|0|0|0|0|0|0|0|0|0|0|0|0|0|0|0|0|0|0|0|0|0|0|0|0|0|0|0|0|0|0|0|0|0|0|0|0|0|0|0|0|0|0|0|0|0|0|0|0|0|0|0|0|0|0|0|0|0|0|0|0|0|0|0|0|0|0|0|0|0|0|0|0|0|0|0|0|0|0|0|0|0|0|0|0|0|0|0|0|0|0|0|0|0|0|0|0|0|0|0|0|0|0|0|0|0|0|0|0|0|0|0|0|0|0|0|0|0|0|0|0|0|0|0|0|0|0|0|0|0|0|0|0|0|0|0|0|0|0|0|0|0|0|0|0|0|0|0|0|0|0|0|0|0|0|0|0|0|0|0|0|0|0|0|0|0|0|0|0|0|0|0|0|0|0|0|0|0|0|0|0|0|0|0|0|0|0|0|0|0|0|0|0|0|0|0|0|0|0|0|0|0|0|0|0|0|0|0|0|0|0|0|0|0|0|0|0|0|0|0|0|0|0|0|0|0|0|0|0|0|0|0|0|0|0|0|0|0|0|0|0|0|0|0|0|0|0|0|0|0|0|0|0|0|0|0|0|0|0|0|0|0|0|0|0|0|0|0|0|0|0|0|0|0|0|0|0|0|0|0|0|0|0|0|0|0|0|0|0|0|1|0|0|0|0|0|0|0|0|0|0|0|1|0|0|0|0|0|0|0|0|0|0|0|1|0|0|0|0|0|0|0|1|0|0|0|0|0|0|1|0|0|0|0|0|0|0|0|0|0|0|0|0|0|0|0|0|0|0|0|0|0|0|0|0|1|1|0|0|0|0|0|0|0|0|0|0|0|0|1|0|0|0|0|0|0|0|0|0|0|0|0|0|0|0|0|0|1|0|0|0|0|0|1|1|1|0|1|0|0|0|0|0|0|0|0|0|0|0|0|0|0|0|0|1|0|0|0|0|0|0|2|0|0|1|0|0|0|0|0|0|0|0|2|0|0|0|0|1|1|0|0|1|0|0|0|0|1|2|0|0|0|0|0|0|0|0|0|0|0|0|1|0|0|1|1|0|0|0|3|1|1|0|0|0|1|0|0|0|0|0|1|1|0|0|2|0|0|0|0|0|0|0|0|0|0|1|0|0|0|0|0|0|3|1|0|0|1|0|0|0|0|0|1|1|0|0|1|0|1|1|1|1|0|0|0|1|0|0|2|0|1|0|1|0|1|1|0|1|0|0|2|1|0|0|0|0|0|2|0|0|0|0|2|1|0|1|1|0|0|0|0|0|1|1|0|0|0|0|0|0|0|1|1|1|0|0|1|1|2|0|1|0|0|0|1|1|1|0|0|0|1|1|1|1|0|2|0|1|1|2|1|1|3|1|1|2|1|4|1|0|1|1|0|1|0|0|0|1|1|1|1|4|0|0|0|0|1|3|0|1|2|3|0|0|1|0|1|0|2|1|0|2|3|0|2|1|0|0|2|0|2|1|1|0|1|1|3|0|3|1|0|2|1|0|1|0|0|2|3|3|1|1|1|0|2|1|0|0|0|0|2|2|0|0|1|2|2|1|0|2|3|1|1|2|0|1|1|1|0|0|1|2|1|0|2|0|2|0|2|2|1|1|3|1|0|1|3|2|1|2|0|1|1|0|3|2|2|0|0|0|1|2|5|4|2|1|3|6|2|4|1|1|3|3|2|3|1|4|1|2|2|2|0|3|2|2|1|4|1|0|3|1|1|6|1|0|2|3|0|6|2|2|1|3|0|2|4|0|1|4|0|3|5|3|2|1|2|1|0|2|1|3|2|7|2|2|1|2|3|3|1|1|0|3|1|4|3|2|2|4|1|2|1|5|2|3|8|2|1|6|1|4|5|2|3|2|1|3|2|0|2|5|2|1|3|2|5|6|3|3|4|9|1|2|7|0|1|4|4|3|3|3|2|3|6|3|1|2|4|6|2|4|2|2|3|5|2|2|5|3|2|2|4|4|2|2|1|5|5|3|5|2|5|2|5|6|2|4|5|4|3|2|1|1|8|5|2|3|2|7|7|3|5|3|5|2|0|4|6|4|0|1|3|4|6|4|2|0|3|5|1|2|1|2|8|3|5|5|5|5|7|3|2|6|1|2|4|4|0|2|3|5|7|2|8|5|4|2|3|1|6|4|4|3|7|2|1|4|3|2|2|5|5|5|2|6|4|6|5|5|5|6|3|6|2|3|4|3|3|7|6|5|0|6|2|1|7|1|4|7|4|4|4|6|6|6|2|5|9|7|8|4|6|5|7|5|11|1|6|8|3|2|5|7|5|3|5|0|5|3|2|1|3|6|4|5|2|5|4|6|2|3|4|6|9|3|7|1|5|4|3|4|4|4|5|8|3|5|5|7|2|6|5|3|5|5|4|4|6|4|6|4|4|8|4|6|6|1|3|6|4|5|2|5|5|4|4|10|2|2|4|6|4|7|6|3|4|6|6|2|8|5|6|2|4|6|5|1|6|5|2|9|6|3|4|4|3|2|1|4|5|4|3|1|2|3|5|2|3|1|3|8|4|6|7|2|4|7|5|5|3|4|6|2|8|4|8|11|7|8|6|10|1|3|5|6|1|4|4|4|5|0|4|6|8|5|6|10|4|6|8|3|4|3|3|3|1|4|1|7|7|2|5|3|5|7|7|2|7|0|0|3|5|5|3|1|2|4|5|2|6|6|4|8|5|5|4|3|2|4|5|7|5|4|7|4|7|3|8|6|4|4|3|7|6|1|3|6|5|1|6|2|6|9|4|7|2|2|4|9|2|5|1|1|7|6|4|2|5|7|3|7|5|6|3|5|8|4|2|3|8|9|3|3|5|5|2|6|6|3|6|7|7|6|2|2|5|6|9|3|6|6|4|2|7|4|3|2|5|6|4|3|4|5|8|4|8|3|5|3|5|2|2|4|5|4|7|5|4|2|3|6|5|2|6|2|4|3|8|3|3|7|7|3|2|4|3|5|3|4|5|6|1|4|5|5|4|3|0|6|0|2|4|3|2|1|3|2|3|3|10|4|2|5|2|5|6|12|3|5|3|6|1|5|4|3|9|7|0|3|1|0|3|2|6|5|4|6|2|3|4|2|3|3|5|3|2|6|4|2|3|4|4|9|1|6|6|6|3|4|2|6|2|5|4|3|3|3|2|1|1|7|5|5|2|5|4|2|7|7|1|3|9|3|4|6|5|5|4|2|3|4|4|1|1|7|1|5|1|4|2|7|1|1|3|0|4|4|7|5|0|2|3|5|3|5|7|2|3|5|4|6|7|3|3|2|2|6|4|3|5|4|1|4|5|3|2|4|3|5|5|1|1|3|3|3|2|2|6|1|2|3|1|3|4|3|4|0|3|7|2|5|3|3|3|3|3|4|2|3|4|5|4|4|4|4|1|2|4|1|3|2|5|3|6|3|1|6|4|1|3|4|4|2|1|2|2|4|3|5|4|3|7|5|2|2|2|3|2|1|1|5|6|0|3|5|3|3|1|3|3|2|2|2|0|2|4|5|4|3|3|1|1|1|1|3|2|3|6|1|2|3|3|0|5|2|4|5|1|4|1|2|0|4|3|3|1|1|4|2|1|1|1|4|2|1|5|3|3|2|1|1|0|3|4|0|1|4|3|3|5|1|2|2|2|1|0|2|3|1|2|3|2|1|2|3|3|2|2|1|1|3|2|2|1|0|5|1|4|1|1|2|3|2|3|2|2|1|2|2|6|1|3|3|2|1|2|4|0|1|3|2|2|0|3|3|2|0|2|0|0|1|1|3|2|6|4|5|1|2|0|0|2|3|1|1|3|0|2|1|2|1|0|6|1|0|2|0|0|2|1|2|0|0|1|1|1|2|1|2|1|3|1|1|4|2|1|4|3|0|1|0|2|0|1|1|1|2|2|2|3|1|2|0|0|0|3|2|0|1|2|1|2|0|3|1|1|4|3|3|1|0|2|1|0|2|1|1|1|1|1|0|2|3|0|3|1|1|2|1|1|2|0|3|3|2|2|5|4|1|2|2|2|1|0|5|0|1|3|1|1|2|1|1|1|1|2|3|2|1|1|0|1|0|0|0|1|1|2|0|5|5|2|3|1|1|1|1|1|0|2|0|0|0|1|2|0|2|1|1|0|3|0|1|0|1|1|2|1|0|1|1|2|3|2|1|0|1|0|2|0|2|1|0|0|2|0|3|0|0|0|2|0|0|1|1|0|2|4|1|0|1|1|0|2|0|0|0|2|0|1|0|0|2|1|0|0|0|2|1|1|0|2|1|2|1|0|0|1|2|0|0|0|2|2|2|0|1|0|0|1|0|0|0|1|1|1|1|1|0|0|1|2|2|0|0|2|0|1|1|0|1|0|2|3|1|1|1|0|0|3|0|0|0|0|0|0|1|0|0|1|1|0|0|0|1|1|1|0|0|1|0|0|1|0|0|0|0|1|1|1|1|0|0|1|1|0|0|3|0|0|1|1|1|0|2|0|0|2|2|0|1|2|0|0|0|4|1|1|0|0|0|0|0|1|0|0|0|0|1|0|1|0|1|0|0|0|0|1|0|0|1|1|0|0|0|0|0|0|1|0|0|1|1|0|0|0|0|1|1|2|1|0|0|0|0|0|0|1|1|0|1|0|0|2|0|1|0|0|0|0|0|0|1|0|0|3|3|1|1|0|0|0|1|0|1|0|1|1|1|4|0|0|0|0|1|0|0|2|1|0|0|0|0|1|0|0|0|0|0|1|0|1|0|0|0|0|0|1|0|0|0|1|1|0|0|2|0|1|0|1|0|0|0|1|0|0|1|0|1|0|0|0|1|0|0|1|0|0|1|0|0|1|0|0|0|0|0|0|0|0|1|0|0|0|0|0|1|0|0|0|1|0|2|0|0|0|0|0|1|0|1|1|0|1|0|0|1|0|2|0|0|1|0|0|0|0|0|0|2|0|1|0|1|0|0|0|1|0|1|0|0|1|0|1|0|1|0|0|2|1|0|0|0|0|0|0|0|0|0|0|0|1|0|0|0|0|0|0|0|1|0|1|0|0|0|0|0|0|0|0|0|0|0|0|0|0|0|0|0|0|0|0|0|1|0|0|0|0|0|0|0|0|0|0|0|0|0|0|0|0|0|0|0|0|0|0|0|0|0|0|0|0|0|0|0|0|0|1|0|0|0|1|0|1|0|0|0|1|0|0|0|0|0|0|0|0|0|0|0|0|1|0|0|0|0|1|0|0|0|1|0|0|0|0|0|1|0|0|0|0|0|0|0|0|0|0|0|0|0|0|0|0|0|0|0|0|0|0|0|0|0|1|0|0|0|0|0|0|0|0|0|0|0|0|0|0|0|0|0|0|0|0|0|0|0|0|0|0|0|0|0|0|0|0|0|0|0|0|0|2|0|0|0|0|0|0|0|0|0|0|1|0|0|0|0|0|0|1|0|0|0|0|0|0|0|0|0|0|0|0|0|0|0|0|0|0|0|1|0|0|0|0|0|0|1|0|0|0|0|0|0|0|0|0|0|0|0|0|1|0|0|0|0|0|0|0|0|2|0|0|0|0|0|0|0|0|0|0|0|1|0|0|0|0|0|0|0|0|0|0|0|0|0|0|0|0|0|0|0|0|0|0|0|0|0|0|0|0|1|0|0|0|0|0|0|0|0|0|0|0|0|0|0|0|0|0|0|0|1|0|0|0|0|0|0|0|0|0|0|0|0|0|0|0|0|0|0|0|0|0|0|0|0|1|0|0|0|0|0|0|0|0|0|0|0|0|0|0|0|0|0|0|0|0|0|0|0|0|0|1|0|0|0|0|0|0|0|0|0|0|0|0|0|0|0|0|0|0|0|0|0|1|0|0|0|0|0|0|0|0|0|0|0|0|0|0|0|1|0|0|0|0|0|0|0|0|0|0|0|0|0|0|0|0|0|0|0|0|0|0|0|0|0|0|0|0|0|0|0|0|0|0|0|0|0|0|0|0|0|0|0|0|0|0|1|0|0|0|0|0|1|0|0|0|0|0|0|0|0|0|0|2</HistCounts>
      </HistItem>
    </Histograms>
    <Metadata>
      <MDI key="STATISTICS_COUNT">4096.000000</MDI>
      <MDI key="STATISTICS_COVARIANCES">1605.777711481155,4689.438532127613,10895.78244953824,9611.597336214147,16542.99127127213,58257.82087578211,80537.81422180231,130573.5036897129,8673.117540922603,73.97836395375468,53032.82620907747,21530.93913261218,97413.47887143225</MDI>
      <MDI key="STATISTICS_EXCLUDEDVALUES"></MDI>
      <MDI key="STATISTICS_MAXIMUM">3067</MDI>
      <MDI key="STATISTICS_MEAN">1635.259765625</MDI>
      <MDI key="STATISTICS_MEDIAN">1607.000000</MDI>
      <MDI key="STATISTICS_MINIMUM">684</MDI>
      <MDI key="STATISTICS_SKIPFACTORX">1</MDI>
      <MDI key="STATISTICS_SKIPFACTORY">1</MDI>
      <MDI key="STATISTICS_STDDEV">361.34955886193</MDI>
    </Metadata>
  </PAMRasterBand>
  <PAMRasterBand band="9">
    <Histograms>
      <HistItem>
        <HistMin>-0.5</HistMin>
        <HistMax>484.5</HistMax>
        <BucketCount>485</BucketCount>
        <IncludeOutOfRange>1</IncludeOutOfRange>
        <Approximate>0</Approximate>
        <HistCounts>0|0|0|0|0|0|0|0|0|0|0|0|0|0|0|0|0|0|0|0|0|0|0|0|0|0|0|0|0|0|0|0|0|0|0|0|0|0|0|0|0|0|0|0|0|0|0|0|0|0|0|0|0|0|0|0|0|0|0|0|0|0|0|0|0|0|0|0|0|0|0|0|0|0|0|0|0|0|0|0|0|0|0|0|0|0|0|0|0|0|0|0|0|0|0|0|0|0|0|0|0|0|0|0|0|0|0|0|0|0|0|0|0|0|0|0|0|0|0|0|0|0|0|0|0|0|0|0|0|0|0|0|0|0|0|0|0|0|0|0|0|0|0|0|0|0|0|0|0|0|0|0|0|0|0|0|0|0|0|0|0|0|0|0|0|0|0|0|0|0|0|0|0|0|0|0|0|0|0|0|0|0|0|0|0|0|0|0|0|0|0|0|0|0|0|0|0|0|0|0|0|0|0|0|0|0|0|0|0|0|0|0|0|0|0|0|0|0|0|0|0|0|0|0|0|0|0|0|0|0|0|0|0|0|0|0|0|0|0|0|0|0|0|0|0|0|0|0|0|0|0|0|0|0|0|0|0|0|4|3|6|5|14|15|15|19|14|16|20|17|26|17|24|31|26|22|28|18|37|37|45|40|36|41|36|31|27|43|35|27|28|31|34|35|24|26|20|20|27|23|22|17|20|23|23|21|19|38|19|31|35|32|16|19|19|19|21|21|16|19|17|11|26|15|21|21|30|41|36|39|49|59|41|44|45|43|42|42|34|36|27|37|40|39|38|26|44|48|45|33|38|45|40|45|52|38|43|73|43|47|36|33|44|25|34|41|32|38|17|23|36|21|26|26|30|17|22|30|16|16|17|15|18|19|6|15|21|10|12|14|19|14|18|12|11|15|20|14|14|23|19|12|9|8|6|9|5|4|6|8|5|2|5|11|4|2|7|4|4|4|3|4|3|2|4|3|2|1|0|0|1|1|0|0|1|3|3|2|1|0|0|0|2|1|0|0|0|3|3|2|0|0|0|0|0|2|1|0|1|0|3|2|0|0|0|0|1|1|1|0|0|1|2|0|1|0|1|0|0|1|0|0|1|0|2</HistCounts>
      </HistItem>
    </Histograms>
    <Metadata>
      <MDI key="STATISTICS_COUNT">4096.000000</MDI>
      <MDI key="STATISTICS_COVARIANCES">304.5766976567097,270.7115868723324,724.5868368556211,736.0653675046769,1842.064488717658,5906.66439964655,8214.420450220325,8673.117540922603,1638.901263390468,13.74066524296012,6270.587742829003,2569.365423785195,10189.66921139295</MDI>
      <MDI key="STATISTICS_EXCLUDEDVALUES"></MDI>
      <MDI key="STATISTICS_MAXIMUM">484</MDI>
      <MDI key="STATISTICS_MEAN">333.82299804688</MDI>
      <MDI key="STATISTICS_MEDIAN">336.000000</MDI>
      <MDI key="STATISTICS_MINIMUM">258</MDI>
      <MDI key="STATISTICS_SKIPFACTORX">1</MDI>
      <MDI key="STATISTICS_SKIPFACTORY">1</MDI>
      <MDI key="STATISTICS_STDDEV">40.483345506399</MDI>
    </Metadata>
  </PAMRasterBand>
  <PAMRasterBand band="10">
    <Histograms>
      <HistItem>
        <HistMin>-0.5</HistMin>
        <HistMax>9.5</HistMax>
        <BucketCount>10</BucketCount>
        <IncludeOutOfRange>1</IncludeOutOfRange>
        <Approximate>0</Approximate>
        <HistCounts>0|0|0|0|35|203|841|1408|1267|342</HistCounts>
      </HistItem>
    </Histograms>
    <Metadata>
      <MDI key="STATISTICS_COUNT">4096.000000</MDI>
      <MDI key="STATISTICS_COVARIANCES">-2.678530947134806,1.209246937957908,5.704201066944792,5.768862859146243,14.55082423544338,43.64193870907697,63.55220531421677,73.97836395375468,13.74066524296012,1.102662295386899,51.20387745392614,21.93520042782722,80.63263358278061</MDI>
      <MDI key="STATISTICS_EXCLUDEDVALUES"></MDI>
      <MDI key="STATISTICS_MAXIMUM">9</MDI>
      <MDI key="STATISTICS_MEAN">7.146240234375</MDI>
      <MDI key="STATISTICS_MEDIAN">7.000000</MDI>
      <MDI key="STATISTICS_MINIMUM">4</MDI>
      <MDI key="STATISTICS_SKIPFACTORX">1</MDI>
      <MDI key="STATISTICS_SKIPFACTORY">1</MDI>
      <MDI key="STATISTICS_STDDEV">1.0500772806736</MDI>
    </Metadata>
  </PAMRasterBand>
  <PAMRasterBand band="11">
    <Histograms>
      <HistItem>
        <HistMin>-0.5</HistMin>
        <HistMax>1747.5</HistMax>
        <BucketCount>1748</BucketCount>
        <IncludeOutOfRange>1</IncludeOutOfRange>
        <Approximate>0</Approximate>
        <HistCounts>0|0|0|0|0|0|0|0|0|0|0|0|0|0|0|0|0|0|0|0|0|0|0|0|0|0|0|0|0|0|0|0|0|0|0|0|0|0|0|0|0|0|0|0|0|0|0|0|0|0|0|0|0|0|0|0|0|0|0|0|0|0|0|0|0|0|0|0|0|0|0|0|0|0|0|0|0|0|0|0|0|0|0|0|0|0|0|0|0|0|0|0|0|0|0|0|0|0|0|0|0|0|0|0|0|0|0|0|0|0|0|0|0|0|0|0|0|0|0|0|0|0|0|0|0|0|0|0|0|0|0|0|0|0|0|0|0|0|0|0|0|0|0|0|0|0|0|0|0|0|0|0|0|0|0|0|0|0|0|0|0|0|0|0|0|0|0|0|0|0|0|0|0|0|0|0|0|0|0|0|0|0|0|0|0|0|0|0|0|0|0|0|0|0|0|0|0|0|0|0|0|0|0|0|0|0|0|0|0|0|0|0|0|0|0|0|0|0|0|0|0|0|0|0|0|0|0|0|0|0|0|0|0|0|0|0|0|0|0|0|0|0|0|0|0|0|0|0|0|0|0|0|0|0|0|0|0|0|0|0|0|0|0|0|0|0|0|0|0|0|0|0|0|0|0|0|0|0|0|0|0|0|0|0|0|0|0|0|0|0|0|0|0|0|0|0|0|0|0|0|0|0|0|0|0|0|0|0|0|0|0|0|0|0|0|0|0|0|0|0|0|0|0|0|0|0|0|0|0|0|0|0|0|0|0|0|0|0|0|0|0|0|0|0|0|0|0|0|0|0|0|0|0|0|2|1|1|0|0|2|0|0|1|2|2|5|1|1|0|2|2|0|1|1|0|2|2|1|3|1|0|4|1|4|0|1|1|2|1|3|2|1|1|1|2|2|0|4|1|0|2|2|2|2|1|6|2|1|3|2|5|1|3|1|5|1|3|7|0|0|7|3|3|3|4|9|8|8|7|4|4|9|10|3|8|8|10|5|8|3|5|5|7|9|9|9|3|7|2|7|8|11|8|6|8|1|4|6|7|7|5|5|6|4|4|10|8|2|8|5|9|10|15|6|10|3|10|13|11|8|7|13|7|8|7|10|9|2|6|12|12|11|13|10|6|3|6|13|8|12|7|7|7|8|9|9|9|2|11|7|12|12|5|9|12|8|10|7|4|9|8|6|13|10|10|8|15|12|7|12|8|7|7|5|5|8|6|9|3|4|6|10|6|5|6|10|5|1|8|3|6|6|6|3|6|4|4|2|3|9|6|8|4|3|2|2|7|7|6|8|7|4|6|5|7|6|5|5|5|9|5|6|9|10|6|4|2|7|6|4|7|8|9|4|6|1|4|9|4|5|1|2|8|9|2|3|5|3|4|6|8|3|6|7|8|5|3|5|1|7|7|8|5|6|3|4|8|8|6|4|2|2|3|2|6|7|5|3|4|2|4|9|5|6|1|7|8|4|1|2|2|3|3|6|2|2|7|5|6|1|3|4|9|4|7|5|7|4|4|2|3|3|4|0|2|2|7|3|2|6|5|1|6|6|5|6|7|2|6|4|4|6|3|4|4|6|5|4|9|4|3|5|4|4|4|6|9|5|0|4|5|5|2|3|9|5|1|11|2|9|4|3|2|2|10|5|5|5|6|3|6|8|5|11|5|3|8|4|2|8|4|2|5|11|6|3|1|5|5|8|4|3|7|5|2|6|8|3|8|3|13|7|6|6|6|3|9|5|6|2|6|7|1|3|7|4|6|6|2|2|3|5|5|9|3|7|5|9|6|9|8|4|3|7|9|8|6|5|4|11|6|8|5|5|10|8|7|2|12|3|8|10|2|6|7|9|3|8|9|7|10|6|2|9|2|5|10|8|7|3|5|13|4|9|8|9|5|13|5|12|6|9|8|10|5|11|10|3|9|11|12|7|14|9|9|4|8|8|9|7|10|8|7|12|4|5|9|7|4|7|5|6|8|11|6|6|6|9|8|8|7|4|3|10|8|3|10|5|8|5|10|9|13|4|14|7|9|6|8|6|12|6|7|11|6|3|4|13|8|8|6|4|5|6|8|4|5|5|4|8|4|4|8|7|5|5|5|8|7|5|6|6|5|9|6|10|4|11|2|11|7|5|8|6|9|6|8|9|7|7|8|6|8|5|3|8|7|6|4|6|5|3|3|4|3|5|2|3|5|5|5|2|2|4|4|6|3|4|5|9|2|3|3|2|6|4|3|1|5|5|4|3|4|5|3|5|0|9|5|5|2|5|5|3|5|3|6|5|4|2|3|3|1|4|1|3|6|6|2|2|4|2|0|4|6|2|4|3|1|3|1|2|2|4|3|2|3|3|8|3|2|3|2|3|1|5|4|4|4|2|3|3|3|2|2|4|3|0|3|1|5|4|4|4|2|5|3|0|3|0|1|4|3|3|6|2|1|3|0|2|1|1|1|1|1|2|3|2|0|3|3|4|2|3|3|1|2|4|0|1|0|0|2|1|2|0|3|0|0|1|1|0|0|1|1|1|3|0|0|1|2|0|0|1|0|2|0|3|1|1|1|0|0|0|0|2|0|3|0|0|1|1|0|2|0|0|2|0|0|2|0|4|1|1|1|0|1|0|0|1|0|1|1|1|0|1|1|0|0|0|1|1|1|0|1|0|0|2|0|0|2|4|0|3|0|1|2|1|1|0|1|0|1|0|0|1|0|0|0|0|1|0|0|1|0|1|0|2|0|0|0|1|0|0|0|0|0|0|2|0|0|0|0|0|2|0|2|1|0|0|1|1|0|0|0|0|0|0|0|0|0|0|1|1|1|0|0|0|0|0|3|0|0|1|0|1|0|1|0|0|1|0|0|0|0|0|1|0|0|1|0|0|1|0|1|0|0|1|0|0|0|0|1|1|1|0|0|0|0|0|0|0|1|0|0|0|0|0|0|1|0|0|1|0|0|0|0|1|0|1|0|1|0|1|0|1|0|0|0|0|0|0|1|0|0|0|1|0|0|0|0|0|1|1|0|0|0|0|0|0|0|1|0|0|1|0|0|2|1|0|0|0|0|0|0|0|0|0|0|0|1|0|0|0|0|0|0|0|0|0|0|0|0|0|0|0|0|0|0|0|0|1|0|0|0|0|0|0|0|0|0|0|1|0|0|1|0|0|0|1|0|0|0|0|0|0|0|1|0|1|0|0|0|0|0|0|0|0|1|0|1|0|0|0|0|0|0|0|1|0|1|0|0|0|0|0|0|0|0|0|0|1|0|0|0|0|0|0|0|0|0|1|1|0|0|0|0|0|1|0|0|0|0|0|0|0|0|0|0|0|0|0|1|0|0|0|1|0|1|1|0|0|0|0|0|0|0|0|0|0|0|0|0|0|0|0|0|0|0|1|0|0|0|1|1|0|0|0|0|0|0|0|0|0|0|0|0|0|0|0|0|0|0|0|0|0|0|0|0|0|0|0|0|0|0|0|0|0|0|0|0|0|1|0|0|0|0|0|1|0|1|0|1|0|0|0|0|0|0|0|0|1|0|0|0|0|0|0|0|0|1|0|0|0|0|0|0|1|0|0|1|0|0|0|0|0|0|0|0|0|0|1|0|0|0|0|0|0|0|1|0|1|0|0|0|0|0|1|0|0|0|0|1|0|0|0|0|0|0|0|0|0|0|0|0|0|1|0|1|0|0|0|0|0|0|0|0|0|0|0|0|0|0|0|0|2|0|0|0|0|0|0|0|1|0|0|1|0|0|1|0|0|0|0|0|0|0|0|0|0|0|0|0|1|0|0|1|0|0|0|1|0|0|0|1|0|0|0|0|0|0|0|0|0|0|0|0|0|0|0|0|0|0|0|0|0|0|0|0|0|0|0|0|0|0|0|0|0|0|0|0|1|0|0|0|0|0|0|0|1|0|0|0|1|0|0|0|0|0|0|0|0|0|0|0|0|0|1</HistCounts>
      </HistItem>
    </Histograms>
    <Metadata>
      <MDI key="STATISTICS_COUNT">4096.000000</MDI>
      <MDI key="STATISTICS_COVARIANCES">1736.991524832612,3232.430717004348,6692.33875170512,7642.572984334446,14621.27666760866,33484.42532391117,43322.67171820145,53032.82620907747,6270.587742829003,51.20387745392614,50870.25046401637,22814.63139874992,56304.03319913051</MDI>
      <MDI key="STATISTICS_EXCLUDEDVALUES"></MDI>
      <MDI key="STATISTICS_MAXIMUM">1747</MDI>
      <MDI key="STATISTICS_MEAN">743.23559570313</MDI>
      <MDI key="STATISTICS_MEDIAN">747.000000</MDI>
      <MDI key="STATISTICS_MINIMUM">354</MDI>
      <MDI key="STATISTICS_SKIPFACTORX">1</MDI>
      <MDI key="STATISTICS_SKIPFACTORY">1</MDI>
      <MDI key="STATISTICS_STDDEV">225.54434256708</MDI>
    </Metadata>
  </PAMRasterBand>
  <PAMRasterBand band="12">
    <Histograms>
      <HistItem>
        <HistMin>-0.5</HistMin>
        <HistMax>850.5</HistMax>
        <BucketCount>851</BucketCount>
        <IncludeOutOfRange>1</IncludeOutOfRange>
        <Approximate>0</Approximate>
        <HistCounts>0|0|0|0|0|0|0|0|0|0|0|0|0|0|0|0|0|0|0|0|0|0|0|0|0|0|0|0|0|0|0|0|0|0|0|0|0|0|0|0|0|0|0|0|0|0|0|0|0|0|0|0|0|0|0|0|0|0|0|0|0|0|0|0|0|0|0|0|0|0|0|0|0|0|0|0|0|0|0|0|0|0|0|0|0|0|0|0|0|0|0|0|0|0|0|0|0|0|0|0|0|0|0|0|0|0|0|0|0|0|0|0|0|0|0|0|0|0|0|0|0|0|0|0|0|0|0|1|1|3|1|1|0|2|4|5|7|2|5|4|6|5|4|2|1|2|9|4|3|7|12|12|17|8|18|11|14|11|11|13|14|19|14|18|18|13|16|19|16|16|25|29|18|17|18|9|26|24|22|23|14|30|21|28|19|23|21|29|26|11|19|21|25|24|19|7|12|17|19|13|15|12|15|14|17|14|10|18|12|14|18|16|24|11|14|16|14|11|12|12|9|16|10|19|9|14|8|12|12|14|16|15|7|12|10|11|9|12|13|17|11|3|9|14|13|8|8|5|13|10|8|8|13|6|11|6|11|5|8|13|12|8|8|6|10|11|14|7|9|12|4|13|12|7|12|12|10|9|17|11|7|10|11|16|14|5|12|12|9|8|12|14|13|21|12|12|9|13|12|9|11|13|15|9|10|14|14|9|12|12|7|14|12|14|14|11|21|11|10|17|21|19|24|5|23|22|16|19|10|16|15|16|23|14|18|26|24|26|25|25|11|25|19|16|17|24|15|12|16|19|18|17|14|18|21|21|18|15|18|16|11|20|26|19|16|17|9|20|12|16|14|17|18|14|12|11|14|13|13|18|15|20|11|14|11|15|12|16|8|10|17|9|8|22|6|10|11|18|6|9|14|2|3|9|13|9|5|11|10|10|7|7|7|4|7|9|7|4|8|4|5|4|4|5|2|2|2|9|3|3|2|1|6|6|3|2|3|4|0|0|2|2|2|3|3|0|3|0|4|3|1|1|7|1|0|0|1|1|0|4|3|2|5|7|4|1|3|1|3|2|3|0|0|2|3|1|0|0|0|3|0|1|1|0|0|1|2|0|0|1|2|2|0|4|1|0|2|4|0|2|0|0|0|4|0|1|0|1|2|0|1|1|0|1|0|1|1|0|0|1|1|0|2|1|0|1|1|2|0|1|0|0|0|1|1|1|0|0|1|0|0|0|0|0|0|0|0|0|0|1|0|1|2|1|2|0|1|0|1|1|0|0|1|0|0|0|0|1|0|0|0|0|0|0|0|0|0|0|0|0|0|0|0|1|0|0|1|2|0|0|0|0|0|0|2|0|0|0|0|0|0|0|0|0|0|1|1|0|0|1|0|0|0|0|0|0|0|1|0|0|1|1|0|0|1|0|0|0|0|0|0|1|0|1|1|0|1|0|0|0|0|0|0|1|0|0|0|0|0|0|0|0|2|0|1|0|0|0|0|0|0|0|0|0|0|0|0|0|0|0|0|0|0|1|1|0|0|0|1|0|2|0|0|0|0|1|0|0|0|0|0|0|0|1|0|0|0|1|0|1|0|0|0|0|0|0|1|0|0|0|0|0|0|0|0|1|0|0|0|1|1|0|1|0|0|2|0|0|0|0|0|0|0|0|0|1|0|0|0|0|0|0|0|0|1|0|0|0|1|0|1|0|0|0|0|0|1|0|1|1|0|1|0|0|0|0|0|0|0|0|0|0|0|0|0|0|1|0|0|0|0|0|0|0|2|1|1|0|0|0|1|0|0|0|1|0|0|1|1|0|0|0|0|1|0|1|0|1|0|0|1|0|0|0|0|0|0|0|0|0|0|0|0|1|0|0|0|0|0|0|0|0|1|0|0|0|0|0|0|0|0|0|0|0|0|1|0|0|0|0|1</HistCounts>
      </HistItem>
    </Histograms>
    <Metadata>
      <MDI key="STATISTICS_COUNT">4096.000000</MDI>
      <MDI key="STATISTICS_COVARIANCES">774.2280408773222,1535.926079107527,3051.581764811807,3663.343040710367,6584.597977418648,13722.78396487949,17417.75211445456,21530.93913261218,2569.365423785195,21.93520042782722,22814.63139874992,10545.43992429558,22904.25610101166</MDI>
      <MDI key="STATISTICS_EXCLUDEDVALUES"></MDI>
      <MDI key="STATISTICS_MAXIMUM">850</MDI>
      <MDI key="STATISTICS_MEAN">291.67504882813</MDI>
      <MDI key="STATISTICS_MEDIAN">293.000000</MDI>
      <MDI key="STATISTICS_MINIMUM">127</MDI>
      <MDI key="STATISTICS_SKIPFACTORX">1</MDI>
      <MDI key="STATISTICS_SKIPFACTORY">1</MDI>
      <MDI key="STATISTICS_STDDEV">102.69099242044</MDI>
    </Metadata>
  </PAMRasterBand>
  <PAMRasterBand band="13">
    <Histograms>
      <HistItem>
        <HistMin>-0.5</HistMin>
        <HistMax>3344.5</HistMax>
        <BucketCount>3345</BucketCount>
        <IncludeOutOfRange>1</IncludeOutOfRange>
        <Approximate>0</Approximate>
        <HistCounts>0|0|0|0|0|0|0|0|0|0|0|0|0|0|0|0|0|0|0|0|0|0|0|0|0|0|0|0|0|0|0|0|0|0|0|0|0|0|0|0|0|0|0|0|0|0|0|0|0|0|0|0|0|0|0|0|0|0|0|0|0|0|0|0|0|0|0|0|0|0|0|0|0|0|0|0|0|0|0|0|0|0|0|0|0|0|0|0|0|0|0|0|0|0|0|0|0|0|0|0|0|0|0|0|0|0|0|0|0|0|0|0|0|0|0|0|0|0|0|0|0|0|0|0|0|0|0|0|0|0|0|0|0|0|0|0|0|0|0|0|0|0|0|0|0|0|0|0|0|0|0|0|0|0|0|0|0|0|0|0|0|0|0|0|0|0|0|0|0|0|0|0|0|0|0|0|0|0|0|0|0|0|0|0|0|0|0|0|0|0|0|0|0|0|0|0|0|0|0|0|0|0|0|0|0|0|0|0|0|0|0|0|0|0|0|0|0|0|0|0|0|0|0|0|0|0|0|0|0|0|0|0|0|0|0|0|0|0|0|0|0|0|0|0|0|0|0|0|0|0|0|0|0|0|0|0|0|0|0|0|0|0|0|0|0|0|0|0|0|0|0|0|0|0|0|0|0|0|0|0|0|0|0|0|0|0|0|0|0|0|0|0|0|0|0|0|0|0|0|0|0|0|0|0|0|0|0|0|0|0|0|0|0|0|0|0|0|0|0|0|0|0|0|0|0|0|0|0|0|0|0|0|0|0|0|0|0|0|0|0|0|0|0|0|0|0|0|0|0|0|0|0|0|0|0|0|0|0|0|0|0|0|0|0|0|0|0|0|0|0|0|0|0|0|0|0|0|0|0|0|0|0|0|0|0|0|0|0|0|0|0|0|0|0|0|0|0|0|0|0|0|0|0|0|0|0|0|0|0|0|0|0|0|0|0|0|0|0|0|0|0|0|0|0|0|0|0|0|0|0|0|0|0|0|0|0|0|0|0|0|0|0|0|0|0|0|0|0|0|0|0|0|0|0|0|0|0|0|0|0|0|0|0|0|0|0|0|0|0|0|0|0|0|0|0|0|0|0|0|0|0|0|0|0|0|0|0|0|0|0|0|0|0|0|0|0|0|0|0|0|0|0|0|0|0|0|0|0|0|0|0|0|0|0|0|0|0|0|0|0|0|0|0|0|0|0|0|0|0|0|0|0|0|0|0|0|0|0|0|0|0|0|0|0|0|0|0|0|0|0|0|0|0|0|0|0|0|0|0|0|0|0|0|0|0|0|0|0|0|0|0|0|0|0|0|0|0|0|0|0|0|0|0|0|0|0|0|0|0|0|0|0|0|0|0|0|0|0|0|0|0|0|0|0|0|0|0|0|0|0|0|0|0|0|0|0|0|0|0|0|0|0|0|0|0|0|0|0|0|0|0|0|0|0|0|0|0|0|0|0|0|0|0|0|0|0|0|0|0|0|0|0|0|0|0|0|0|0|0|0|0|0|0|0|0|0|0|0|0|0|0|0|0|0|0|0|0|0|0|0|0|0|0|0|0|0|0|0|0|0|0|0|0|0|0|0|0|0|0|0|0|0|0|0|0|0|0|0|0|0|0|0|0|0|0|0|0|0|0|0|0|0|0|0|0|0|0|0|0|0|0|0|0|0|0|0|0|0|0|0|0|0|0|0|0|0|0|0|0|0|0|0|0|0|0|0|0|0|0|0|0|0|0|0|0|0|0|0|0|0|0|0|0|0|0|0|0|0|0|0|0|0|0|0|0|0|0|0|0|0|0|0|0|0|0|0|0|0|0|0|0|0|0|0|0|0|0|0|0|0|0|0|0|0|0|0|0|0|0|0|0|0|0|0|0|0|0|0|0|0|0|0|0|0|0|0|0|0|0|0|0|0|0|0|0|0|0|0|0|0|0|0|0|0|0|0|0|0|0|0|0|0|0|0|0|0|0|0|0|0|0|0|0|0|0|0|0|0|0|0|0|0|0|0|0|0|0|0|0|0|0|0|0|0|0|0|0|0|0|0|0|0|0|0|0|0|0|0|0|0|0|0|0|0|0|0|0|0|0|0|0|0|0|0|0|0|0|0|0|0|0|0|0|0|0|0|0|0|0|0|0|0|0|0|0|0|0|0|0|0|0|0|0|0|0|0|0|0|0|0|0|0|0|0|0|0|0|0|0|0|0|0|0|0|0|0|0|0|0|0|0|0|0|0|0|0|0|0|0|0|0|0|0|0|0|0|0|0|0|0|0|0|0|0|0|0|0|0|0|0|0|0|0|0|0|0|0|0|0|0|0|0|0|0|0|0|0|0|0|0|0|0|0|0|0|0|0|0|0|0|0|0|0|0|0|0|0|0|0|0|0|0|0|0|0|0|0|0|0|0|0|0|0|0|0|0|0|0|0|0|0|0|0|0|0|0|0|0|0|0|0|0|0|0|0|0|0|0|0|0|0|0|0|0|0|0|0|0|0|0|0|0|0|0|1|0|0|0|0|0|0|0|0|0|0|0|0|0|0|0|0|0|0|0|0|0|0|0|0|0|0|0|0|0|0|0|0|0|2|0|0|0|0|0|0|0|0|1|0|0|0|0|0|0|1|0|0|2|0|0|0|0|0|0|0|0|1|0|0|0|0|0|0|0|0|0|0|0|0|1|0|1|1|0|0|0|1|0|1|0|0|0|0|0|1|0|0|0|0|0|0|0|1|0|0|0|0|1|0|0|0|0|0|0|0|0|0|0|0|1|0|0|0|0|0|1|0|0|0|0|0|0|0|0|1|0|0|0|0|0|0|1|1|0|0|1|1|0|0|0|0|1|1|0|0|0|0|0|0|0|0|0|1|0|0|1|0|0|2|0|0|0|0|2|0|2|1|0|1|0|0|0|2|0|0|0|0|0|0|0|0|1|0|0|0|1|0|1|1|1|0|2|0|1|1|0|0|0|0|0|0|0|3|2|0|1|0|1|2|0|1|0|2|1|0|1|0|1|0|1|1|2|0|0|1|2|0|0|0|0|1|0|0|1|1|0|1|1|2|0|1|1|1|1|1|0|5|2|0|1|1|0|1|2|1|0|4|0|2|0|4|1|4|3|2|1|0|0|3|2|0|1|4|1|0|1|1|1|3|4|2|1|1|1|4|2|2|4|1|1|0|3|4|3|4|2|1|1|1|3|1|0|3|4|4|0|1|1|3|2|0|0|3|1|3|3|2|2|0|2|4|3|4|2|0|2|2|1|1|3|4|2|2|1|2|1|3|2|3|0|0|1|0|3|3|3|1|3|2|2|4|1|1|3|2|2|2|1|4|2|1|2|0|0|2|2|1|3|1|1|3|2|0|3|3|1|4|2|2|3|0|2|1|1|2|1|4|2|2|2|4|2|4|1|1|2|1|1|2|8|4|4|4|2|0|2|3|6|4|2|5|8|3|4|4|3|4|2|3|2|3|6|5|3|2|9|2|2|4|3|3|4|1|3|4|1|1|2|2|2|3|4|3|1|3|2|5|4|5|4|3|2|1|7|2|6|5|3|4|4|0|3|2|3|2|1|2|2|2|1|1|3|8|1|10|5|6|1|1|5|1|2|2|1|4|4|1|3|5|1|3|3|5|2|1|6|2|5|7|7|6|1|3|4|5|3|4|1|3|5|2|2|2|3|3|4|9|4|2|2|4|4|7|7|5|9|5|4|9|4|3|3|6|3|5|2|2|4|2|4|3|5|3|2|3|0|1|3|3|3|4|4|8|3|3|9|5|2|7|4|5|2|5|4|5|12|2|3|4|6|4|3|5|6|5|6|6|10|3|3|4|11|2|1|1|5|5|6|4|4|3|5|1|3|6|2|5|6|5|6|3|5|2|5|7|9|5|5|3|3|6|8|2|4|1|3|6|6|3|6|3|6|5|6|7|4|6|6|6|6|8|1|4|4|3|8|5|8|6|1|4|7|2|10|6|4|4|5|3|2|5|4|8|4|6|3|7|1|4|10|3|5|5|5|3|6|7|5|4|7|8|3|5|3|5|3|1|6|5|11|1|3|2|5|10|14|7|5|3|8|7|3|9|1|7|8|6|5|7|9|1|4|5|6|11|9|8|6|4|10|8|5|9|8|4|6|8|8|6|3|2|8|4|0|5|3|8|7|6|3|4|2|4|6|7|7|4|4|1|5|7|8|4|7|5|9|4|4|6|10|7|6|5|5|8|6|4|2|4|3|6|6|4|7|4|5|3|4|9|6|4|10|5|5|7|5|3|7|6|2|6|6|7|6|4|6|7|7|5|6|4|8|2|9|4|9|8|9|5|6|6|3|5|7|9|6|7|5|8|4|6|2|8|5|4|8|6|4|3|4|7|6|4|11|7|5|6|9|5|5|6|6|1|7|6|3|6|2|5|6|7|5|10|2|8|8|8|8|0|8|3|9|9|6|6|5|6|11|6|4|7|4|7|3|9|5|5|3|6|5|4|4|8|5|3|8|3|2|2|2|4|9|3|3|2|9|6|3|3|2|3|5|2|5|9|2|6|4|8|4|7|3|2|4|3|5|5|6|5|5|3|5|5|2|7|1|4|2|5|5|4|5|3|4|3|0|2|7|3|3|4|2|6|5|8|10|2|7|2|3|5|7|5|2|10|3|4|6|5|5|7|4|7|4|6|5|5|5|1|2|2|3|5|2|2|4|5|4|2|6|7|5|3|4|5|6|5|1|9|4|4|1|4|3|5|2|7|6|3|0|4|3|3|2|5|2|7|4|5|2|0|2|5|3|3|7|4|3|4|5|6|4|2|4|8|3|4|4|3|3|1|4|6|5|0|4|4|4|4|3|6|3|1|1|3|3|5|7|5|0|3|1|4|4|4|2|1|5|3|8|5|3|5|1|4|4|4|2|4|5|5|2|1|2|2|4|2|3|1|6|4|3|1|1|7|3|2|2|1|4|4|3|3|5|5|7|1|3|0|1|0|1|4|4|0|4|3|4|4|1|3|3|5|1|1|3|1|0|4|3|4|1|1|3|1|3|3|3|2|0|3|2|0|2|0|0|2|4|1|0|2|3|1|2|0|2|2|1|1|3|1|1|1|2|3|1|3|1|1|2|1|3|3|1|1|2|0|0|2|0|2|3|1|0|2|2|2|3|3|2|1|2|1|1|3|2|0|2|0|2|0|1|1|1|0|1|3|1|1|3|0|2|1|0|1|1|2|1|2|2|0|2|2|1|1|2|5|3|0|1|0|2|0|0|1|0|1|2|1|2|1|1|6|3|0|1|2|2|0|1|2|0|4|5|0|1|0|1|1|1|1|3|2|3|0|1|0|2|2|2|0|0|3|6|2|4|0|2|1|1|0|0|1|4|0|2|1|2|0|3|1|1|0|2|0|1|3|0|0|1|0|2|1|3|0|2|2|3|0|6|3|0|0|2|4|3|0|0|1|2|2|2|1|2|0|0|2|1|1|1|2|1|0|2|1|3|1|3|4|0|2|3|1|2|4|0|0|0|0|0|1|2|0|0|2|0|1|0|0|3|0|2|1|0|0|0|1|1|0|2|3|0|2|2|3|4|0|0|0|0|1|3|2|4|0|0|0|2|1|0|1|2|0|3|0|1|0|0|0|0|0|0|2|1|1|0|1|0|0|1|2|0|2|1|1|1|0|3|1|0|2|1|2|0|0|2|0|1|0|0|1|0|5|2|0|1|0|1|0|1|0|1|2|3|1|0|2|1|0|1|2|0|2|1|1|1|1|0|0|1|2|1|2|1|0|0|0|0|3|0|0|2|3|2|2|2|0|0|0|2|0|0|0|1|2|0|1|1|3|1|1|0|0|2|1|1|1|0|0|0|0|1|1|0|0|0|1|3|1|0|0|0|0|1|0|2|1|0|1|0|1|1|0|0|2|1|0|1|2|1|1|0|0|1|1|0|0|0|0|0|1|1|0|1|1|1|1|0|0|0|0|0|1|0|0|0|1|0|2|1|1|1|0|2|2|1|0|0|0|2|0|0|0|0|0|1|0|0|1|0|1|2|0|1|0|0|1|0|0|0|0|1|0|1|0|0|1|0|0|0|2|1|0|0|0|0|0|0|0|0|0|0|2|2|0|1|1|0|0|0|0|1|0|0|0|0|0|0|0|1|1|0|0|0|0|0|1|0|0|0|0|1|1|1|1|1|0|0|0|0|0|1|0|2|0|0|0|0|0|0|0|0|1|1|0|0|0|1|0|0|0|1|0|0|0|0|0|2|1|0|0|0|0|0|0|1|0|0|0|0|0|0|1|0|0|0|0|1|1|0|1|0|0|0|1|0|0|0|1|0|0|0|0|0|0|0|0|0|0|0|0|0|1|0|0|0|0|0|0|0|1|0|0|0|0|0|0|0|0|0|0|0|0|0|0|0|0|1|1|0|0|0|0|0|0|0|0|0|0|0|0|1|0|1|0|0|0|0|0|0|1|0|0|0|0|0|1|0|0|0|0|0|0|0|0|0|0|0|0|0|0|0|0|0|0|1|0|0|0|0|0|0|0|0|0|1|0|0|0|0|0|0|0|0|0|0|0|0|0|0|0|0|0|0|0|0|0|0|0|0|0|0|0|0|0|0|0|0|0|0|0|0|0|0|0|0|0|0|0|0|1|0|0|0|0|0|0|0|0|0|1|0|0|0|0|0|0|0|0|0|0|0|0|0|0|0|0|0|0|0|0|0|0|0|0|0|0|0|0|0|0|0|0|0|0|0|0|0|0|0|0|0|0|0|0|0|0|0|0|0|0|0|0|0|0|0|0|0|0|0|2|0|0|0|0|0|0|0|0|0|0|0|0|0|0|0|0|0|0|0|0|0|0|0|0|0|0|0|0|0|0|0|0|0|0|0|0|0|0|0|0|0|0|0|0|0|0|0|0|0|0|0|0|0|0|1|0|0|0|0|0|0|0|0|0|0|0|0|0|0|0|0|1|0|0|0|0|0|0|0|0|0|1|0|0|0|0|0|0|0|0|0|0|0|0|0|0|0|0|0|0|0|0|0|0|0|0|0|0|0|0|0|0|0|0|0|0|0|0|0|0|0|0|0|0|0|0|0|0|0|0|0|0|0|0|0|0|0|0|0|0|0|0|0|0|0|0|0|0|0|0|0|0|0|0|1|0|0|0|0|0|0|0|0|0|0|0|0|0|0|0|0|0|0|0|0|0|0|0|0|0|1|0|0|0|0|0|1|0|0|0|0|0|0|0|0|0|0|0|1|0|0|0|0|0|0|0|0|0|0|0|0|0|0|0|0|0|0|0|0|0|0|0|0|0|0|0|0|0|0|0|0|0|0|0|0|0|0|0|0|0|0|0|0|0|0|0|0|0|0|0|0|1|0|0|0|0|0|0|0|0|0|0|0|0|0|0|0|0|0|0|0|0|0|0|0|0|0|0|0|0|0|0|0|0|0|0|0|0|0|0|0|0|0|0|0|0|0|0|0|0|0|0|0|0|0|0|0|0|0|0|0|0|0|0|0|1|0|0|0|0|0|0|0|0|0|0|0|0|0|0|0|0|0|1</HistCounts>
      </HistItem>
    </Histograms>
    <Metadata>
      <MDI key="STATISTICS_COUNT">4096.000000</MDI>
      <MDI key="STATISTICS_COVARIANCES">1949.552840675946,3507.847462368369,8158.090980389969,7702.413214297659,17043.01461821064,58578.06473852212,80733.15825594759,97413.47887143225,10189.66921139295,80.63263358278061,56304.03319913051,22904.25610101166,99098.83586112835</MDI>
      <MDI key="STATISTICS_EXCLUDEDVALUES"></MDI>
      <MDI key="STATISTICS_MAXIMUM">3344</MDI>
      <MDI key="STATISTICS_MEAN">1905.7067871094</MDI>
      <MDI key="STATISTICS_MEDIAN">1884.000000</MDI>
      <MDI key="STATISTICS_MINIMUM">1104</MDI>
      <MDI key="STATISTICS_SKIPFACTORX">1</MDI>
      <MDI key="STATISTICS_SKIPFACTORY">1</MDI>
      <MDI key="STATISTICS_STDDEV">314.79967576401</MDI>
    </Metadata>
  </PAMRasterBand>
</PAMDataset>
