<PAMDataset>
  <PAMRasterBand band="1">
    <Histograms>
      <HistItem>
        <HistMin>1240</HistMin>
        <HistMax>1493</HistMax>
        <BucketCount>256</BucketCount>
        <IncludeOutOfRange>1</IncludeOutOfRange>
        <Approximate>0</Approximate>
        <HistCounts>1|1|3|3|1|1|2|6|1|2|2|0|2|3|5|3|1|4|1|1|2|2|5|2|4|3|4|4|8|5|9|13|13|19|15|11|23|30|18|29|14|27|28|25|23|30|30|24|26|34|39|24|26|26|24|26|31|28|37|31|33|24|31|33|35|32|31|41|27|23|32|40|39|34|36|32|41|27|33|34|50|37|45|35|38|35|38|43|29|33|26|31|43|37|34|26|37|38|29|38|31|23|35|39|33|38|37|25|38|50|37|41|30|34|32|34|48|27|40|32|32|34|32|28|31|31|34|0|28|28|23|30|24|29|14|13|13|11|13|18|18|17|20|5|12|7|16|12|13|18|13|16|11|9|10|12|9|15|5|5|12|5|20|11|7|7|10|10|5|5|12|11|10|9|8|7|10|11|5|9|5|8|9|2|10|6|5|6|8|7|10|6|5|5|5|7|6|4|5|8|8|5|5|8|1|11|3|6|6|3|6|3|12|5|6|5|4|2|4|2|4|4|4|2|5|3|2|4|3|2|2|3|1|5|0|0|1|1|3|2|3|1|0|2|2|1|1|2|1|2|1|0|3|1|0|1</HistCounts>
      </HistItem>
    </Histograms>
    <Metadata>
      <MDI key="STATISTICS_COUNT">4096.000000</MDI>
      <MDI key="STATISTICS_COVARIANCES">2149.074379423754,4663.166832586907,5544.431039007659,11514.7945676177,7735.820486289972,-7012.229053270818,-10704.87230229064,-11123.86554051941,-1962.32306303175,1.179572554181869,10958.55426712494,14380.04082412811,-12123.83585367529</MDI>
      <MDI key="STATISTICS_EXCLUDEDVALUES"></MDI>
      <MDI key="STATISTICS_MAXIMUM">1493</MDI>
      <MDI key="STATISTICS_MEAN">1340.4406738281</MDI>
      <MDI key="STATISTICS_MEDIAN">1334.254902</MDI>
      <MDI key="STATISTICS_MINIMUM">1240</MDI>
      <MDI key="STATISTICS_SKIPFACTORX">1</MDI>
      <MDI key="STATISTICS_SKIPFACTORY">1</MDI>
      <MDI key="STATISTICS_STDDEV">46.358110179598</MDI>
    </Metadata>
  </PAMRasterBand>
  <PAMRasterBand band="2">
    <Histograms>
      <HistItem>
        <HistMin>860</HistMin>
        <HistMax>1669</HistMax>
        <BucketCount>256</BucketCount>
        <IncludeOutOfRange>1</IncludeOutOfRange>
        <Approximate>0</Approximate>
        <HistCounts>1|0|0|3|0|4|1|1|1|1|3|1|3|2|2|6|3|15|19|15|16|25|28|26|33|16|29|21|22|19|30|20|27|15|30|24|29|27|17|19|30|34|21|24|37|37|57|40|39|40|47|42|57|50|41|42|39|61|34|32|33|28|36|57|51|41|44|33|51|67|49|36|46|34|37|55|42|47|48|31|39|49|20|29|24|30|31|32|24|21|27|29|40|19|28|14|17|19|31|15|22|17|21|22|22|29|13|13|19|15|24|17|16|15|16|20|25|16|22|22|22|29|16|17|25|21|12|24|17|16|17|21|12|24|18|16|18|18|19|13|18|13|9|16|15|12|8|10|12|10|11|13|10|14|11|10|12|14|8|12|11|12|12|8|8|9|16|10|16|10|15|5|5|11|7|5|3|3|3|2|7|9|3|6|7|11|3|2|2|1|2|6|8|2|4|9|4|6|4|3|2|0|3|4|3|1|1|0|3|1|4|0|2|1|2|0|0|0|3|0|2|1|2|1|1|0|1|1|1|0|2|3|0|1|3|0|1|0|1|0|2|3|2|1|2|1|0|2|0|0|0|0|0|0|0|1</HistCounts>
      </HistItem>
    </Histograms>
    <Metadata>
      <MDI key="STATISTICS_COUNT">4096.000000</MDI>
      <MDI key="STATISTICS_COVARIANCES">4663.166832586907,21078.99997180004,25641.45944779505,51937.02544273216,29006.72914252083,-25071.91298088841,-39016.10966922084,-48302.45178183884,-4942.097598002031,13.67305927579356,37700.7507887023,49505.7160168175,-43750.58180052385</MDI>
      <MDI key="STATISTICS_EXCLUDEDVALUES"></MDI>
      <MDI key="STATISTICS_MAXIMUM">1669</MDI>
      <MDI key="STATISTICS_MEAN">1133.5871582031</MDI>
      <MDI key="STATISTICS_MEDIAN">1097.941176</MDI>
      <MDI key="STATISTICS_MINIMUM">860</MDI>
      <MDI key="STATISTICS_SKIPFACTORX">1</MDI>
      <MDI key="STATISTICS_SKIPFACTORY">1</MDI>
      <MDI key="STATISTICS_STDDEV">145.18608739063</MDI>
    </Metadata>
  </PAMRasterBand>
  <PAMRasterBand band="3">
    <Histograms>
      <HistItem>
        <HistMin>730</HistMin>
        <HistMax>1815</HistMax>
        <BucketCount>256</BucketCount>
        <IncludeOutOfRange>1</IncludeOutOfRange>
        <Approximate>0</Approximate>
        <HistCounts>1|1|1|0|1|0|0|1|0|0|2|2|1|2|2|1|4|1|3|3|2|3|2|1|3|4|2|4|4|1|7|6|5|8|11|9|15|13|22|31|18|29|28|26|31|31|15|29|18|28|23|34|33|35|31|33|27|24|31|28|33|21|34|29|41|34|36|42|29|34|36|49|45|56|67|51|46|55|62|43|46|54|72|32|51|32|50|26|35|47|59|29|33|42|49|37|32|37|47|27|39|37|38|33|30|31|28|30|14|33|32|24|29|34|18|22|19|29|20|23|15|23|15|13|26|26|13|27|14|24|25|28|22|28|24|13|15|17|23|15|26|25|16|20|20|16|18|13|8|15|16|15|15|19|11|15|24|7|18|12|20|16|13|10|16|9|17|9|10|10|10|4|8|5|14|9|8|4|2|5|7|2|5|8|5|4|6|7|4|2|5|3|6|6|6|5|3|3|3|5|1|3|4|3|8|2|4|7|4|0|1|6|2|2|0|1|3|0|2|2|3|1|1|2|0|0|0|0|2|1|0|1|1|0|1|0|1|2|2|0|0|1|1|2|0|1|0|4|1|3|2|2|0|2|0|1</HistCounts>
      </HistItem>
    </Histograms>
    <Metadata>
      <MDI key="STATISTICS_COUNT">4096.000000</MDI>
      <MDI key="STATISTICS_COVARIANCES">5544.431039007659,25641.45944779505,32715.59734044716,63089.30737024469,36574.22619912105,-25079.41797006143,-41143.8744069676,-50775.93890874182,-5232.354531834176,17.04278130723469,45582.54580608721,58063.95106098319,-46335.0659277462</MDI>
      <MDI key="STATISTICS_EXCLUDEDVALUES"></MDI>
      <MDI key="STATISTICS_MAXIMUM">1815</MDI>
      <MDI key="STATISTICS_MEAN">1149.1794433594</MDI>
      <MDI key="STATISTICS_MEDIAN">1112.941176</MDI>
      <MDI key="STATISTICS_MINIMUM">730</MDI>
      <MDI key="STATISTICS_SKIPFACTORX">1</MDI>
      <MDI key="STATISTICS_SKIPFACTORY">1</MDI>
      <MDI key="STATISTICS_STDDEV">180.87453480368</MDI>
    </Metadata>
  </PAMRasterBand>
  <PAMRasterBand band="4">
    <Histograms>
      <HistItem>
        <HistMin>464</HistMin>
        <HistMax>2242</HistMax>
        <BucketCount>256</BucketCount>
        <IncludeOutOfRange>1</IncludeOutOfRange>
        <Approximate>0</Approximate>
        <HistCounts>3|10|21|45|41|34|15|18|12|9|11|7|18|8|8|13|14|11|17|10|23|14|19|17|15|17|21|20|20|20|16|23|22|33|20|34|29|37|23|36|28|38|39|35|37|50|34|51|45|54|33|30|39|39|35|50|43|42|35|46|42|32|36|43|36|38|37|30|37|38|36|24|28|34|29|26|19|29|18|36|34|27|22|29|23|21|25|17|23|24|22|21|29|24|15|17|22|8|14|19|19|21|13|29|20|21|10|16|11|21|26|18|21|19|25|27|16|16|18|19|17|9|20|17|21|16|20|11|26|17|17|11|23|19|22|17|17|14|17|18|12|18|13|18|16|14|7|14|7|10|16|14|13|10|20|10|6|11|8|16|7|18|10|12|15|14|11|14|17|14|15|9|16|10|14|8|4|13|9|9|9|3|9|10|6|8|2|3|6|1|0|3|7|5|4|1|4|4|5|3|7|4|4|3|5|1|6|4|1|3|4|3|3|1|2|2|2|1|2|1|0|1|0|3|2|2|0|2|2|1|3|1|2|0|1|1|3|0|0|0|1|2|2|1|1|2|1|1|1|2|2|2|0|3|0|1</HistCounts>
      </HistItem>
    </Histograms>
    <Metadata>
      <MDI key="STATISTICS_COUNT">4096.000000</MDI>
      <MDI key="STATISTICS_COVARIANCES">11514.7945676177,51937.02544273216,63089.30737024469,132584.4316599414,72579.92797964856,-76822.86720633981,-115350.0383128483,-140990.0160305295,-14573.83883654326,43.66353498931529,93671.30172597583,125738.3016087645,-127802.3970121245</MDI>
      <MDI key="STATISTICS_EXCLUDEDVALUES"></MDI>
      <MDI key="STATISTICS_MAXIMUM">2242</MDI>
      <MDI key="STATISTICS_MEAN">1056.5092773437</MDI>
      <MDI key="STATISTICS_MEDIAN">972.996078</MDI>
      <MDI key="STATISTICS_MINIMUM">464</MDI>
      <MDI key="STATISTICS_SKIPFACTORX">1</MDI>
      <MDI key="STATISTICS_SKIPFACTORY">1</MDI>
      <MDI key="STATISTICS_STDDEV">364.12145179863</MDI>
    </Metadata>
  </PAMRasterBand>
  <PAMRasterBand band="5">
    <Histograms>
      <HistItem>
        <HistMin>883</HistMin>
        <HistMax>2296</HistMax>
        <BucketCount>256</BucketCount>
        <IncludeOutOfRange>1</IncludeOutOfRange>
        <Approximate>0</Approximate>
        <HistCounts>1|0|1|0|1|1|1|0|0|0|0|0|2|2|1|1|0|3|11|5|6|8|11|7|12|9|12|14|11|15|17|12|12|15|6|6|8|14|18|15|13|11|16|11|16|11|20|19|19|21|19|30|15|29|15|26|22|31|43|30|31|25|35|27|33|29|43|35|43|33|47|22|47|42|36|39|44|46|56|44|57|59|44|52|44|41|57|45|44|36|38|43|75|41|47|49|52|36|44|42|49|56|33|40|30|58|34|37|39|52|44|29|31|27|31|30|32|26|36|26|41|35|31|33|26|26|19|27|17|18|15|20|21|24|17|21|24|3|16|15|25|17|17|12|14|13|15|10|15|21|9|10|12|8|6|11|15|8|7|14|12|5|8|3|10|4|11|5|4|8|8|6|5|8|6|12|3|5|5|6|7|1|8|2|4|5|7|5|2|3|2|5|5|1|4|3|1|5|4|1|0|4|1|2|0|3|1|4|1|0|0|0|1|1|1|0|1|1|1|0|1|3|2|2|0|0|1|1|1|1|2|0|0|0|1|1|0|1|3|1|3|0|1|1|3|1|1|1|1|1|0|0|3|1|0|1</HistCounts>
      </HistItem>
    </Histograms>
    <Metadata>
      <MDI key="STATISTICS_COUNT">4096.000000</MDI>
      <MDI key="STATISTICS_COVARIANCES">7735.820486289972,29006.72914252083,36574.22619912105,72579.92797964856,47827.29200429018,-35269.19186090599,-57218.01219922108,-64609.56826368599,-7558.926480642794,26.59967137896794,61425.51598897511,76389.24110553086,-63315.99813093829</MDI>
      <MDI key="STATISTICS_EXCLUDEDVALUES"></MDI>
      <MDI key="STATISTICS_MAXIMUM">2296</MDI>
      <MDI key="STATISTICS_MEAN">1417.5900878906</MDI>
      <MDI key="STATISTICS_MEDIAN">1392.788235</MDI>
      <MDI key="STATISTICS_MINIMUM">883</MDI>
      <MDI key="STATISTICS_SKIPFACTORX">1</MDI>
      <MDI key="STATISTICS_SKIPFACTORY">1</MDI>
      <MDI key="STATISTICS_STDDEV">218.69451754511</MDI>
    </Metadata>
  </PAMRasterBand>
  <PAMRasterBand band="6">
    <Histograms>
      <HistItem>
        <HistMin>1755</HistMin>
        <HistMax>4261</HistMax>
        <BucketCount>256</BucketCount>
        <IncludeOutOfRange>1</IncludeOutOfRange>
        <Approximate>0</Approximate>
        <HistCounts>2|3|4|0|4|1|8|6|7|9|15|6|11|13|10|8|12|17|11|13|13|13|20|12|13|18|21|19|16|26|16|21|20|31|36|36|24|33|47|34|25|42|44|35|49|63|38|41|51|47|54|42|38|36|44|50|42|45|41|41|66|45|53|39|44|56|52|31|45|38|52|39|47|48|43|53|47|59|57|42|56|33|44|55|50|40|45|32|23|26|26|32|23|32|30|23|28|33|30|27|26|36|30|34|31|41|29|27|23|29|13|17|18|14|12|15|16|17|18|23|14|15|9|9|10|13|3|13|9|6|11|12|6|10|7|10|7|7|3|4|6|5|7|1|6|9|9|1|4|4|0|4|4|6|1|3|3|2|1|4|2|5|2|4|3|3|0|1|2|1|2|6|3|4|7|4|3|7|3|3|4|4|5|6|6|7|2|4|5|2|5|3|0|2|2|2|4|5|2|0|2|1|3|2|2|2|3|6|1|0|6|7|2|1|3|3|2|2|1|1|3|0|3|2|1|1|1|3|0|2|1|0|2|3|0|0|1|1|0|4|1|1|0|2|0|1|0|2|1|1|1|1|1|2|0|1</HistCounts>
      </HistItem>
    </Histograms>
    <Metadata>
      <MDI key="STATISTICS_COUNT">4096.000000</MDI>
      <MDI key="STATISTICS_COVARIANCES">-7012.229053270818,-25071.91298088841,-25079.41797006143,-76822.86720633981,-35269.19186090599,171598.8788211134,229076.8042392835,247691.3743257057,34040.14267506568,-38.95236282814467,-37338.15084838088,-77964.824288862,244848.0238894133</MDI>
      <MDI key="STATISTICS_EXCLUDEDVALUES"></MDI>
      <MDI key="STATISTICS_MAXIMUM">4261</MDI>
      <MDI key="STATISTICS_MEAN">2520.5844726562</MDI>
      <MDI key="STATISTICS_MEDIAN">2452.749020</MDI>
      <MDI key="STATISTICS_MINIMUM">1755</MDI>
      <MDI key="STATISTICS_SKIPFACTORX">1</MDI>
      <MDI key="STATISTICS_SKIPFACTORY">1</MDI>
      <MDI key="STATISTICS_STDDEV">414.24495026628</MDI>
    </Metadata>
  </PAMRasterBand>
  <PAMRasterBand band="7">
    <Histograms>
      <HistItem>
        <HistMin>1963</HistMin>
        <HistMax>5297</HistMax>
        <BucketCount>256</BucketCount>
        <IncludeOutOfRange>1</IncludeOutOfRange>
        <Approximate>0</Approximate>
        <HistCounts>2|1|4|4|2|3|7|11|9|16|9|13|11|18|9|14|14|10|14|22|14|15|27|27|20|20|24|38|29|30|28|28|27|34|38|33|40|47|46|55|49|34|41|41|48|36|31|46|44|43|61|46|50|47|45|49|46|50|56|49|50|41|44|47|57|43|58|43|54|38|60|65|52|31|48|56|48|47|50|37|30|31|27|29|29|27|25|27|33|32|40|43|29|37|38|35|28|28|29|21|23|19|25|20|19|23|14|15|14|13|21|17|19|18|21|12|13|13|8|12|9|14|10|8|10|7|12|9|13|9|3|8|6|9|3|4|7|4|5|5|4|10|10|2|2|2|2|4|6|2|2|3|3|1|5|3|4|2|0|3|3|2|4|0|2|3|0|1|1|0|4|1|5|5|3|4|2|6|4|7|2|3|2|3|9|5|13|1|2|3|7|2|2|3|2|2|0|4|5|1|1|2|1|6|3|1|3|3|5|0|2|2|0|5|5|4|1|3|3|0|1|2|3|0|2|1|0|1|1|2|1|2|2|3|1|0|0|0|2|0|4|3|0|0|1|0|1|1|1|3|0|0|1|1|1|1</HistCounts>
      </HistItem>
    </Histograms>
    <Metadata>
      <MDI key="STATISTICS_COUNT">4096.000000</MDI>
      <MDI key="STATISTICS_COVARIANCES">-10704.87230229064,-39016.10966922084,-41143.8744069676,-115350.0383128483,-57218.01219922108,229076.8042392835,309934.1633837354,336084.2998034358,45749.15117515405,-51.83348357371806,-62735.01191698341,-117308.2859725561,331188.8382909072</MDI>
      <MDI key="STATISTICS_EXCLUDEDVALUES"></MDI>
      <MDI key="STATISTICS_MAXIMUM">5297</MDI>
      <MDI key="STATISTICS_MEAN">2928.4050292969</MDI>
      <MDI key="STATISTICS_MEDIAN">2825.917647</MDI>
      <MDI key="STATISTICS_MINIMUM">1963</MDI>
      <MDI key="STATISTICS_SKIPFACTORX">1</MDI>
      <MDI key="STATISTICS_SKIPFACTORY">1</MDI>
      <MDI key="STATISTICS_STDDEV">556.71731011685</MDI>
    </Metadata>
  </PAMRasterBand>
  <PAMRasterBand band="8">
    <Histograms>
      <HistItem>
        <HistMin>1789</HistMin>
        <HistMax>5439</HistMax>
        <BucketCount>256</BucketCount>
        <IncludeOutOfRange>1</IncludeOutOfRange>
        <Approximate>0</Approximate>
        <HistCounts>1|3|1|0|3|0|4|3|6|2|3|5|10|6|3|18|13|15|19|20|24|28|31|28|28|25|26|23|28|25|24|30|34|40|35|36|47|29|30|47|43|43|42|52|42|45|36|30|36|34|46|56|61|49|51|42|32|52|33|41|41|42|48|44|36|46|34|56|46|49|41|44|38|42|49|47|51|46|38|36|38|33|31|36|31|37|42|29|25|47|43|41|43|43|32|34|34|31|26|20|28|25|25|36|17|20|24|25|24|16|15|21|17|14|15|13|11|12|22|10|11|13|9|16|13|11|10|8|15|6|8|4|5|7|5|9|1|9|4|3|5|4|4|4|6|3|4|4|3|4|5|1|1|4|8|0|5|3|1|5|3|3|5|4|2|4|6|8|4|5|4|5|5|7|6|8|1|2|4|9|5|4|3|3|13|6|6|3|7|4|4|5|5|4|3|1|2|5|7|2|3|4|1|2|1|1|0|5|2|1|3|1|2|0|3|1|2|0|2|1|2|1|0|2|1|3|3|2|1|2|0|1|1|1|0|2|1|1|2|3|1|2|0|2|4|2|0|4|1|1|1|3|2|1|0|1</HistCounts>
      </HistItem>
    </Histograms>
    <Metadata>
      <MDI key="STATISTICS_COUNT">4096.000000</MDI>
      <MDI key="STATISTICS_COVARIANCES">-11123.86554051941,-48302.45178183884,-50775.93890874182,-140990.0160305295,-64609.56826368599,247691.3743257057,336084.2998034358,398843.7511460597,46224.32728884055,-52.77864154075279,-71190.3089775181,-131883.8625808433,359376.7767610324</MDI>
      <MDI key="STATISTICS_EXCLUDEDVALUES"></MDI>
      <MDI key="STATISTICS_MAXIMUM">5439</MDI>
      <MDI key="STATISTICS_MEAN">2895.0827636719</MDI>
      <MDI key="STATISTICS_MEDIAN">2776.647059</MDI>
      <MDI key="STATISTICS_MINIMUM">1789</MDI>
      <MDI key="STATISTICS_SKIPFACTORX">1</MDI>
      <MDI key="STATISTICS_SKIPFACTORY">1</MDI>
      <MDI key="STATISTICS_STDDEV">631.54077552131</MDI>
    </Metadata>
  </PAMRasterBand>
  <PAMRasterBand band="9">
    <Histograms>
      <HistItem>
        <HistMin>744</HistMin>
        <HistMax>1265</HistMax>
        <BucketCount>256</BucketCount>
        <IncludeOutOfRange>1</IncludeOutOfRange>
        <Approximate>0</Approximate>
        <HistCounts>9|5|10|9|4|13|14|13|14|13|15|13|17|13|14|15|19|15|24|36|27|31|52|68|36|51|40|47|36|39|40|35|30|36|36|46|63|50|41|56|51|69|54|49|54|52|80|62|41|47|61|44|73|69|71|64|67|48|43|53|47|52|31|31|38|30|34|34|25|43|30|29|32|14|30|14|24|16|19|18|14|21|18|25|13|19|17|16|19|17|21|22|29|25|26|14|20|21|26|18|18|18|18|28|18|19|14|25|19|17|31|25|25|13|15|25|21|16|17|9|19|10|5|17|12|21|7|5|4|5|3|1|3|4|6|4|3|3|3|2|2|2|4|2|8|2|6|5|3|2|2|4|3|3|0|2|4|1|4|2|2|3|4|5|4|5|1|5|1|3|3|2|1|2|1|1|3|1|5|3|1|2|4|7|4|6|1|1|2|0|0|3|2|2|2|3|1|1|3|9|4|1|2|1|4|1|2|1|2|2|2|4|1|1|4|3|1|3|3|1|1|5|2|3|1|0|2|0|4|0|2|4|5|2|1|0|3|3|1|1|0|3|0|2|5|2|0|2|2|0|1|4|1|2|1|1</HistCounts>
      </HistItem>
    </Histograms>
    <Metadata>
      <MDI key="STATISTICS_COUNT">4096.000000</MDI>
      <MDI key="STATISTICS_COVARIANCES">-1962.32306303175,-4942.097598002031,-5232.354531834176,-14573.83883654326,-7558.926480642794,34040.14267506568,45749.15117515405,46224.32728884055,8662.124860193013,-3.955488305097886,-7291.122357021092,-15924.17420324909,49405.53097730174</MDI>
      <MDI key="STATISTICS_EXCLUDEDVALUES"></MDI>
      <MDI key="STATISTICS_MAXIMUM">1265</MDI>
      <MDI key="STATISTICS_MEAN">882.35620117188</MDI>
      <MDI key="STATISTICS_MEDIAN">856.372549</MDI>
      <MDI key="STATISTICS_MINIMUM">744</MDI>
      <MDI key="STATISTICS_SKIPFACTORX">1</MDI>
      <MDI key="STATISTICS_SKIPFACTORY">1</MDI>
      <MDI key="STATISTICS_STDDEV">93.070537014638</MDI>
    </Metadata>
  </PAMRasterBand>
  <PAMRasterBand band="10">
    <Histograms>
      <HistItem>
        <HistMin>9</HistMin>
        <HistMax>12</HistMax>
        <BucketCount>256</BucketCount>
        <IncludeOutOfRange>1</IncludeOutOfRange>
        <Approximate>0</Approximate>
        <HistCounts>192|0|0|0|0|0|0|0|0|0|0|0|0|0|0|0|0|0|0|0|0|0|0|0|0|0|0|0|0|0|0|0|0|0|0|0|0|0|0|0|0|0|0|0|0|0|0|0|0|0|0|0|0|0|0|0|0|0|0|0|0|0|0|0|0|0|0|0|0|0|0|0|0|0|0|0|0|0|0|0|0|0|0|0|0|1701|0|0|0|0|0|0|0|0|0|0|0|0|0|0|0|0|0|0|0|0|0|0|0|0|0|0|0|0|0|0|0|0|0|0|0|0|0|0|0|0|0|0|0|0|0|0|0|0|0|0|0|0|0|0|0|0|0|0|0|0|0|0|0|0|0|0|0|0|0|0|0|0|0|0|0|0|0|0|0|0|0|0|0|0|1646|0|0|0|0|0|0|0|0|0|0|0|0|0|0|0|0|0|0|0|0|0|0|0|0|0|0|0|0|0|0|0|0|0|0|0|0|0|0|0|0|0|0|0|0|0|0|0|0|0|0|0|0|0|0|0|0|0|0|0|0|0|0|0|0|0|0|0|0|0|0|0|0|0|0|0|0|0|0|0|0|0|0|0|0|557</HistCounts>
      </HistItem>
    </Histograms>
    <Metadata>
      <MDI key="STATISTICS_COUNT">4096.000000</MDI>
      <MDI key="STATISTICS_COVARIANCES">1.179572554181869,13.67305927579356,17.04278130723469,43.66353498931529,26.59967137896794,-38.95236282814467,-51.83348357371806,-52.77864154075279,-3.955488305097886,0.5997519841269767,33.92965935973793,41.16703105921787,-52.87102125305279</MDI>
      <MDI key="STATISTICS_EXCLUDEDVALUES"></MDI>
      <MDI key="STATISTICS_MAXIMUM">12</MDI>
      <MDI key="STATISTICS_MEAN">10.626953125</MDI>
      <MDI key="STATISTICS_MEDIAN">11.000000</MDI>
      <MDI key="STATISTICS_MINIMUM">9</MDI>
      <MDI key="STATISTICS_SKIPFACTORX">1</MDI>
      <MDI key="STATISTICS_SKIPFACTORY">1</MDI>
      <MDI key="STATISTICS_STDDEV">0.77443655913637</MDI>
    </Metadata>
  </PAMRasterBand>
  <PAMRasterBand band="11">
    <Histograms>
      <HistItem>
        <HistMin>1597</HistMin>
        <HistMax>3522</HistMax>
        <BucketCount>256</BucketCount>
        <IncludeOutOfRange>1</IncludeOutOfRange>
        <Approximate>0</Approximate>
        <HistCounts>1|2|0|0|0|0|1|0|3|1|1|0|1|3|4|2|2|4|1|6|1|4|1|3|3|4|1|1|3|2|3|1|3|1|3|8|1|4|7|3|2|3|2|3|5|2|4|6|3|15|10|8|20|15|16|14|21|13|14|17|22|14|27|21|17|17|22|24|22|23|24|28|29|30|35|28|28|33|28|40|42|47|33|41|41|48|34|54|38|45|38|46|44|36|44|34|35|36|54|37|51|45|52|44|43|46|48|38|40|45|43|42|46|44|54|37|46|42|49|46|49|43|36|52|31|36|29|49|34|43|25|32|27|32|28|20|36|17|30|18|25|18|25|22|19|28|21|13|23|29|12|23|11|14|19|20|14|20|18|9|9|8|10|15|7|10|12|17|7|17|11|14|13|7|9|6|10|9|5|5|6|8|13|7|4|9|9|7|11|13|10|8|9|7|2|6|7|3|8|6|8|2|7|7|6|4|2|6|3|7|1|7|2|3|4|5|8|3|4|7|3|4|4|4|5|4|2|0|1|2|2|3|0|5|0|2|1|2|2|0|1|3|1|2|1|1|2|0|4|3|3|2|0|2|2|1</HistCounts>
      </HistItem>
    </Histograms>
    <Metadata>
      <MDI key="STATISTICS_COUNT">4096.000000</MDI>
      <MDI key="STATISTICS_COVARIANCES">10958.55426712494,37700.7507887023,45582.54580608721,93671.30172597583,61425.51598897511,-37338.15084838088,-62735.01191698341,-71190.3089775181,-7291.122357021092,33.92965935973793,98476.08730820473,114000.3401654549,-69652.1894272499</MDI>
      <MDI key="STATISTICS_EXCLUDEDVALUES"></MDI>
      <MDI key="STATISTICS_MAXIMUM">3522</MDI>
      <MDI key="STATISTICS_MEAN">2455.7087402344</MDI>
      <MDI key="STATISTICS_MEDIAN">2419.843137</MDI>
      <MDI key="STATISTICS_MINIMUM">1597</MDI>
      <MDI key="STATISTICS_SKIPFACTORX">1</MDI>
      <MDI key="STATISTICS_SKIPFACTORY">1</MDI>
      <MDI key="STATISTICS_STDDEV">313.80899813135</MDI>
    </Metadata>
  </PAMRasterBand>
  <PAMRasterBand band="12">
    <Histograms>
      <HistItem>
        <HistMin>780</HistMin>
        <HistMax>2851</HistMax>
        <BucketCount>256</BucketCount>
        <IncludeOutOfRange>1</IncludeOutOfRange>
        <Approximate>0</Approximate>
        <HistCounts>1|1|1|0|1|6|12|16|15|17|9|6|10|9|9|6|10|10|5|7|10|7|7|8|7|11|7|9|10|10|12|19|21|23|22|17|20|23|24|22|23|35|25|23|13|23|25|31|30|30|27|26|44|23|33|32|24|38|24|43|37|32|36|31|36|42|28|42|40|32|29|40|38|25|49|36|41|35|41|39|27|53|58|43|51|41|48|40|43|40|45|49|43|41|32|42|36|34|41|23|29|54|45|47|32|22|34|42|26|19|29|17|24|19|24|37|23|22|35|20|23|19|13|20|18|12|16|17|14|16|23|20|10|12|13|9|7|17|17|15|14|17|7|8|6|13|14|10|15|5|11|11|5|7|5|5|5|11|5|8|5|7|5|12|6|9|7|5|14|10|7|7|13|9|6|7|6|17|5|8|4|7|8|9|12|5|10|4|9|8|3|5|7|8|6|7|6|10|2|5|7|6|5|7|5|7|3|2|3|2|4|5|3|6|2|1|1|1|3|3|2|1|3|3|1|0|0|3|1|3|2|0|2|1|0|2|1|3|0|2|2|0|2|1|0|4|1|3|2|2|3|1|0|3|1|1</HistCounts>
      </HistItem>
    </Histograms>
    <Metadata>
      <MDI key="STATISTICS_COUNT">4096.000000</MDI>
      <MDI key="STATISTICS_COVARIANCES">14380.04082412811,49505.7160168175,58063.95106098319,125738.3016087645,76389.24110553086,-77964.824288862,-117308.2859725561,-131883.8625808433,-15924.17420324909,41.16703105921787,114000.3401654549,147783.9402920866,-130375.1947291863</MDI>
      <MDI key="STATISTICS_EXCLUDEDVALUES"></MDI>
      <MDI key="STATISTICS_MAXIMUM">2851</MDI>
      <MDI key="STATISTICS_MEAN">1535.3134765625</MDI>
      <MDI key="STATISTICS_MEDIAN">1478.454902</MDI>
      <MDI key="STATISTICS_MINIMUM">780</MDI>
      <MDI key="STATISTICS_SKIPFACTORX">1</MDI>
      <MDI key="STATISTICS_SKIPFACTORY">1</MDI>
      <MDI key="STATISTICS_STDDEV">384.42676843852</MDI>
    </Metadata>
  </PAMRasterBand>
  <PAMRasterBand band="13">
    <Histograms>
      <HistItem>
        <HistMin>2226</HistMin>
        <HistMax>5689</HistMax>
        <BucketCount>256</BucketCount>
        <IncludeOutOfRange>1</IncludeOutOfRange>
        <Approximate>0</Approximate>
        <HistCounts>2|4|3|4|6|4|4|2|7|15|13|14|11|16|11|15|19|13|17|7|18|42|29|25|34|25|33|26|27|33|23|25|40|28|44|35|56|38|48|38|38|42|41|44|40|41|42|42|51|61|41|46|53|43|47|54|47|53|56|48|47|39|59|50|45|39|48|48|45|43|51|41|60|43|41|54|31|46|31|39|35|28|33|28|29|14|32|23|23|18|31|35|39|27|38|31|39|40|24|34|26|26|21|21|13|21|15|21|13|7|24|15|16|14|11|14|11|13|10|13|9|13|16|12|15|9|6|10|9|8|9|12|10|9|6|8|4|10|6|6|1|4|4|6|4|7|5|4|5|4|4|6|4|3|1|2|2|2|7|1|2|3|1|1|1|1|3|2|2|2|3|2|1|2|2|1|3|3|1|3|1|3|6|2|5|6|3|8|4|7|6|5|4|5|4|2|2|2|1|5|2|3|0|4|2|1|4|2|3|3|1|3|3|3|3|4|1|4|3|3|0|4|1|2|3|1|4|2|2|2|1|1|2|2|1|2|0|0|1|1|2|2|2|2|0|0|1|1|1|1|1|2|1|2|0|1</HistCounts>
      </HistItem>
    </Histograms>
    <Metadata>
      <MDI key="STATISTICS_COUNT">4096.000000</MDI>
      <MDI key="STATISTICS_COVARIANCES">-12123.83585367529,-43750.58180052385,-46335.0659277462,-127802.3970121245,-63315.99813093829,244848.0238894133,331188.8382909072,359376.7767610324,49405.53097730174,-52.87102125305279,-69652.1894272499,-130375.1947291863,355872.0738264546</MDI>
      <MDI key="STATISTICS_EXCLUDEDVALUES"></MDI>
      <MDI key="STATISTICS_MAXIMUM">5689</MDI>
      <MDI key="STATISTICS_MEAN">3229.5727539063</MDI>
      <MDI key="STATISTICS_MEDIAN">3108.725490</MDI>
      <MDI key="STATISTICS_MINIMUM">2226</MDI>
      <MDI key="STATISTICS_SKIPFACTORX">1</MDI>
      <MDI key="STATISTICS_SKIPFACTORY">1</MDI>
      <MDI key="STATISTICS_STDDEV">596.55014359772</MDI>
    </Metadata>
  </PAMRasterBand>
</PAMDataset>
